[
  {
    "id": 1,
    "category": "クラウドの概念",
    "basic": {
      "question": "クラウドコンピューティングの利点として正しいものはどれか。",
      "choices": [
        "初期投資が大きい",
        "スケーラビリティが高い",
        "物理サーバーの管理が必要",
        "容量の変更ができない"
      ],
      "answer": 1
    },
    "exam": {
      "question": "クラウドコンピューティングの特徴として、正しくないものはどれか。",
      "choices": [
        "必要に応じてリソースを増減できる",
        "使用した分だけ課金される",
        "物理的なデータセンターの管理は利用者が行う",
        "高可用性を実現できる"
      ],
      "answer": 2
    },
    "explanation": "クラウドコンピューティングでは物理的なデータセンターの管理はクラウドプロバイダーが行う。利用者はインフラの物理管理から解放され、スケーラビリティや従量課金のメリットを享受できる。"
  },
  {
    "id": 2,
    "category": "クラウドの概念",
    "basic": {
      "question": "IaaSで利用者が管理する範囲はどれか。",
      "choices": [
        "物理サーバー",
        "OS・ミドルウェア・アプリケーション",
        "データセンターの電源",
        "ネットワークケーブル"
      ],
      "answer": 1
    },
    "exam": {
      "question": "クラウドサービスモデルの責任範囲に関する記述として、正しいものはどれか。",
      "choices": [
        "SaaSでは利用者がOSの管理を行う",
        "PaaSでは利用者がアプリケーションの管理を行う",
        "IaaSではプロバイダーがアプリケーションを管理する",
        "すべてのモデルでネットワーク機器は利用者が管理する"
      ],
      "answer": 1
    },
    "explanation": "PaaSでは利用者はアプリケーションとデータの管理を行い、OS・ミドルウェア・ランタイムはプロバイダーが管理する。IaaSではOS以上を利用者が管理し、SaaSではほぼすべてをプロバイダーが管理する。"
  },
  {
    "id": 3,
    "category": "クラウドの概念",
    "basic": {
      "question": "パブリッククラウドの特徴はどれか。",
      "choices": [
        "自社専用のデータセンターを持つ",
        "不特定多数の利用者がリソースを共有する",
        "インターネット接続が不要",
        "初期費用が非常に高い"
      ],
      "answer": 1
    },
    "exam": {
      "question": "ハイブリッドクラウドに関する記述として、正しいものはどれか。",
      "choices": [
        "パブリッククラウドのみを使用する形態である",
        "オンプレミスとパブリッククラウドを組み合わせた形態である",
        "プライベートクラウドのみを使用する形態である",
        "クラウドを一切使用しない形態である"
      ],
      "answer": 1
    },
    "explanation": "ハイブリッドクラウドはオンプレミス（またはプライベートクラウド）とパブリッククラウドを組み合わせた形態。それぞれの利点を活かし柔軟な運用が可能。"
  },
  {
    "id": 4,
    "category": "クラウドの概念",
    "basic": {
      "question": "CapEx（資本的支出）に該当するものはどれか。",
      "choices": [
        "月額のクラウド利用料",
        "物理サーバーの購入費",
        "従量課金のストレージ料金",
        "サブスクリプション費用"
      ],
      "answer": 1
    },
    "exam": {
      "question": "クラウドの経済性に関する記述として、正しいものはどれか。",
      "choices": [
        "クラウドはCapExモデルである",
        "クラウドはOpEx（運用費）モデルで従量課金が基本である",
        "オンプレミスはOpExモデルである",
        "クラウドでは初期投資が必須である"
      ],
      "answer": 1
    },
    "explanation": "クラウドはOpEx（運用費）モデルで使った分だけ支払う従量課金が基本。オンプレミスはCapEx（資本的支出）モデルでハードウェアの事前購入が必要。"
  },
  {
    "id": 5,
    "category": "クラウドの概念",
    "basic": {
      "question": "SLA（サービスレベルアグリーメント）とは何か。",
      "choices": [
        "料金プラン",
        "サービスの稼働率や品質に関する保証",
        "プログラミング言語",
        "ネットワークの種類"
      ],
      "answer": 1
    },
    "exam": {
      "question": "AzureのSLAに関する記述として、正しいものはどれか。",
      "choices": [
        "すべてのサービスのSLAは100%である",
        "SLAを満たさない場合はサービスクレジットが提供される",
        "SLAは利用者が自由に設定できる",
        "無料サービスにもSLAが保証される"
      ],
      "answer": 1
    },
    "explanation": "AzureのSLAはサービスごとに定められた稼働率の保証。SLAを満たさない場合はサービスクレジット（返金）が提供される。無料サービスにはSLAは適用されない。"
  },
  {
    "id": 6,
    "category": "クラウドの概念",
    "basic": {
      "question": "クラウドの「高可用性」とは何か。",
      "choices": [
        "コストが安いこと",
        "システムが長時間停止せず稼働し続けること",
        "データを暗号化すること",
        "処理速度が速いこと"
      ],
      "answer": 1
    },
    "exam": {
      "question": "高可用性を実現するためのAzureの仕組みとして、正しくないものはどれか。",
      "choices": [
        "可用性ゾーンによる冗長化",
        "リージョンペアによる災害対策",
        "Azure Load Balancerによる負荷分散",
        "単一のVMのみでの運用"
      ],
      "answer": 3
    },
    "explanation": "高可用性は可用性ゾーン、リージョンペア、ロードバランサーなどの冗長構成で実現する。単一VMのみでの運用は単一障害点となり高可用性とは言えない。"
  },
  {
    "id": 7,
    "category": "クラウドの概念",
    "basic": {
      "question": "「スケーラビリティ」の意味として正しいものはどれか。",
      "choices": [
        "セキュリティが高いこと",
        "需要に応じてリソースを増減できること",
        "料金が固定であること",
        "データが暗号化されること"
      ],
      "answer": 1
    },
    "exam": {
      "question": "垂直スケーリングと水平スケーリングに関する記述として、正しいものはどれか。",
      "choices": [
        "垂直スケーリングはVM数を増やすことである",
        "水平スケーリングは1台のVMのCPU/メモリを増やすことである",
        "垂直スケーリングは1台のVMの性能を上げることである",
        "水平スケーリングと垂直スケーリングに違いはない"
      ],
      "answer": 2
    },
    "explanation": "垂直スケーリング（スケールアップ）は1台のリソースの性能を上げること。水平スケーリング（スケールアウト）はリソースの数を増やすこと。目的に応じて使い分ける。"
  },
  {
    "id": 8,
    "category": "クラウドの概念",
    "basic": {
      "question": "「弾力性（Elasticity）」の意味として正しいものはどれか。",
      "choices": [
        "手動でのみリソースを変更できる",
        "需要の変動に合わせて自動的にリソースを増減できる",
        "リソースは一度確保すると変更できない",
        "常に最大リソースを確保すること"
      ],
      "answer": 1
    },
    "exam": {
      "question": "弾力性に関する記述として、正しくないものはどれか。",
      "choices": [
        "需要増加時に自動的にリソースを追加できる",
        "需要減少時にリソースを縮小しコストを削減できる",
        "自動スケーリング機能で実現できる",
        "事前に最大容量を購入しておく必要がある"
      ],
      "answer": 3
    },
    "explanation": "弾力性はクラウドの特徴で、需要に応じてリソースが自動的に増減する。事前に最大容量を購入する必要はなく、使った分だけ支払うモデル。"
  },
  {
    "id": 9,
    "category": "クラウドの概念",
    "basic": {
      "question": "SaaSの具体例として正しいものはどれか。",
      "choices": [
        "Azure Virtual Machines",
        "Azure App Service",
        "Microsoft 365",
        "Azure Kubernetes Service"
      ],
      "answer": 2
    },
    "exam": {
      "question": "SaaSに関する記述として、正しいものはどれか。",
      "choices": [
        "利用者がOSのパッチ管理を行う",
        "利用者はアプリケーションをそのまま利用し、インフラ管理は不要である",
        "利用者が仮想マシンのサイズを選択する",
        "利用者がミドルウェアをインストールする"
      ],
      "answer": 1
    },
    "explanation": "SaaS（Software as a Service）は完成したアプリケーションをそのまま利用する形態。Microsoft 365やSalesforceが代表例。インフラ、OS、アプリすべてプロバイダーが管理する。"
  },
  {
    "id": 10,
    "category": "クラウドの概念",
    "basic": {
      "question": "プライベートクラウドの特徴はどれか。",
      "choices": [
        "不特定多数が利用する",
        "特定の組織専用で運用される",
        "無料で利用できる",
        "インターネット上に公開される"
      ],
      "answer": 1
    },
    "exam": {
      "question": "プライベートクラウドの利点として、正しいものはどれか。",
      "choices": [
        "初期コストが不要である",
        "セキュリティとコンプライアンスの制御が最も高い",
        "パブリッククラウドより常にコストが低い",
        "スケーラビリティがパブリッククラウドより高い"
      ],
      "answer": 1
    },
    "explanation": "プライベートクラウドは特定組織専用のため、セキュリティポリシーやコンプライアンス要件を完全に制御できる。ただし初期コストや運用負担はパブリッククラウドより大きい。"
  },
  {
    "id": 11,
    "category": "クラウドの概念",
    "basic": {
      "question": "「従量課金制」の意味として正しいものはどれか。",
      "choices": [
        "年間契約で定額を支払う",
        "使用したリソース量に応じて課金される",
        "無料で無制限に使える",
        "最初に全額を前払いする"
      ],
      "answer": 1
    },
    "exam": {
      "question": "クラウドの従量課金に関する記述として、正しくないものはどれか。",
      "choices": [
        "使用したコンピューティングリソースに対して課金される",
        "不要なリソースを停止すれば課金を止められる",
        "ストレージの使用量に応じて課金される",
        "一度プロビジョニングしたリソースは削除しても課金が続く"
      ],
      "answer": 3
    },
    "explanation": "クラウドの従量課金ではリソースを削除・停止すれば課金は止まる。使用した分だけ支払うため、不要なリソースの削除がコスト最適化の基本。"
  },
  {
    "id": 12,
    "category": "クラウドの概念",
    "basic": {
      "question": "「災害復旧（ディザスタリカバリ）」の目的はどれか。",
      "choices": [
        "日常的なバックアップ",
        "災害時にシステムを迅速に復旧すること",
        "パフォーマンスの向上",
        "コスト削減"
      ],
      "answer": 1
    },
    "exam": {
      "question": "クラウドにおける災害復旧に関する記述として、正しいものはどれか。",
      "choices": [
        "災害復旧にはクラウドは不向きである",
        "地理的に離れたリージョンへのレプリケーションが有効である",
        "単一のデータセンターに集約するのが最善である",
        "災害復旧計画は不要である"
      ],
      "answer": 1
    },
    "explanation": "クラウドでの災害復旧は地理的に離れたリージョンへのデータレプリケーションやフェイルオーバーにより実現する。Azureのリージョンペアはこの目的で設計されている。"
  },
  {
    "id": 13,
    "category": "クラウドの概念",
    "basic": {
      "question": "「共有責任モデル」とは何か。",
      "choices": [
        "すべての責任がプロバイダーにある",
        "セキュリティの責任をプロバイダーと利用者で分担する",
        "すべての責任が利用者にある",
        "責任の所在が不明確なモデル"
      ],
      "answer": 1
    },
    "exam": {
      "question": "共有責任モデルに関する記述として、正しくないものはどれか。",
      "choices": [
        "物理インフラのセキュリティはプロバイダーの責任である",
        "データの分類とラベル付けは利用者の責任である",
        "アカウントとIDの管理は利用者の責任である",
        "サービスモデルに関わらず責任範囲は常に同じである"
      ],
      "answer": 3
    },
    "explanation": "共有責任モデルではサービスモデル（IaaS/PaaS/SaaS）により利用者とプロバイダーの責任範囲が変わる。SaaSではプロバイダーの責任が最も大きく、IaaSでは利用者の責任が大きい。"
  },
  {
    "id": 14,
    "category": "クラウドの概念",
    "basic": {
      "question": "クラウドの「俊敏性（Agility）」とは何か。",
      "choices": [
        "リソースを素早くデプロイ・変更できること",
        "ネットワーク速度が速いこと",
        "セキュリティが強固なこと",
        "コストが安いこと"
      ],
      "answer": 0
    },
    "exam": {
      "question": "クラウドの俊敏性に関する記述として、正しいものはどれか。",
      "choices": [
        "新しいリソースのプロビジョニングに数週間かかる",
        "数分でインフラをデプロイし迅速にビジネス要件に対応できる",
        "物理サーバーの調達が必要なため対応が遅い",
        "一度構築した環境は変更できない"
      ],
      "answer": 1
    },
    "explanation": "クラウドの俊敏性とは、必要なリソースを数分でプロビジョニングし、ビジネス要件の変化に迅速に対応できること。オンプレミスでは数週間かかる調達が不要になる。"
  },
  {
    "id": 15,
    "category": "クラウドの概念",
    "basic": {
      "question": "マルチクラウドとは何か。",
      "choices": [
        "1つのクラウドプロバイダーのみを使用する",
        "複数のクラウドプロバイダーを組み合わせて使用する",
        "クラウドを使用しないこと",
        "プライベートクラウドの別名"
      ],
      "answer": 1
    },
    "exam": {
      "question": "マルチクラウド戦略の利点として、正しいものはどれか。",
      "choices": [
        "管理が必ず簡単になる",
        "特定プロバイダーへの依存（ベンダーロックイン）を軽減できる",
        "コストは必ず下がる",
        "セキュリティリスクがなくなる"
      ],
      "answer": 1
    },
    "explanation": "マルチクラウドは複数のクラウドプロバイダーを使う戦略。ベンダーロックインの回避、各プロバイダーの強みの活用が利点。ただし管理の複雑さは増す。"
  },
  {
    "id": 16,
    "category": "クラウドの概念",
    "basic": {
      "question": "PaaSの具体例として正しいものはどれか。",
      "choices": [
        "仮想マシン",
        "Azure App Service",
        "Microsoft Word",
        "物理サーバー"
      ],
      "answer": 1
    },
    "exam": {
      "question": "PaaSの特徴に関する記述として、正しくないものはどれか。",
      "choices": [
        "アプリケーションの開発・デプロイに集中できる",
        "OSやミドルウェアはプロバイダーが管理する",
        "利用者はOSのパッチ適用を行う必要がある",
        "開発フレームワークやツールが提供される"
      ],
      "answer": 2
    },
    "explanation": "PaaSではOSやミドルウェアの管理（パッチ適用含む）はプロバイダーが行う。利用者はアプリケーションの開発とデプロイに集中できる。"
  },
  {
    "id": 17,
    "category": "クラウドの概念",
    "basic": {
      "question": "クラウドコンピューティングで「信頼性」が確保される理由はどれか。",
      "choices": [
        "単一のサーバーで運用するから",
        "世界中に分散されたインフラで冗長性があるから",
        "ユーザーが直接管理するから",
        "インターネット接続が不要だから"
      ],
      "answer": 1
    },
    "exam": {
      "question": "クラウドの信頼性に関する記述として、正しいものの組合せはどれか。\n\nA. 分散設計により単一障害点を排除できる\nB. 自動フェイルオーバーで障害時も継続稼働できる\nC. 信頼性のために単一リージョンに集中すべき\nD. バックアップは不要である",
      "choices": [
        "AとB",
        "AとC",
        "BとD",
        "CとD"
      ],
      "answer": 0
    },
    "explanation": "クラウドの信頼性は分散設計と冗長化により実現される。自動フェイルオーバーや複数リージョンへの分散で単一障害点を排除し、障害時も継続稼働する。"
  },
  {
    "id": 18,
    "category": "クラウドの概念",
    "basic": {
      "question": "「ガバナンス」とは何か。",
      "choices": [
        "ネットワーク速度の管理",
        "組織のルールやポリシーに基づいたIT資源の管理統制",
        "データの暗号化",
        "アプリケーション開発"
      ],
      "answer": 1
    },
    "exam": {
      "question": "クラウドガバナンスに関する記述として、正しいものはどれか。",
      "choices": [
        "クラウドではガバナンスは不要である",
        "クラウドのテンプレートやポリシーにより一貫した標準を適用できる",
        "ガバナンスはオンプレミスでのみ実現できる",
        "ガバナンスはコストに影響しない"
      ],
      "answer": 1
    },
    "explanation": "クラウドではAzure PolicyやBlueprints等のツールで、組織全体に一貫したルール（リージョン制限、タグ必須等）を自動的に適用でき、ガバナンスを効率的に実現できる。"
  },
  {
    "id": 19,
    "category": "クラウドの概念",
    "basic": {
      "question": "クラウドの「地理的分散」の利点はどれか。",
      "choices": [
        "コストが増加する",
        "ユーザーに近い場所からサービスを提供しレイテンシを低減する",
        "管理が複雑になるだけ",
        "セキュリティが低下する"
      ],
      "answer": 1
    },
    "exam": {
      "question": "地理的分散に関する記述として、正しくないものはどれか。",
      "choices": [
        "ユーザーに近いリージョンを選ぶとレイテンシが低減する",
        "複数リージョンに展開すると災害対策になる",
        "データ主権の要件に応じてリージョンを選択できる",
        "すべてのデータは必ず1つのリージョンに保存すべきである"
      ],
      "answer": 3
    },
    "explanation": "クラウドの地理的分散はレイテンシの低減、災害対策、データ主権への対応に有効。要件に応じて複数リージョンへの展開やデータのレプリケーションを行う。"
  },
  {
    "id": 20,
    "category": "クラウドの概念",
    "basic": {
      "question": "IaaSの具体例として正しいものはどれか。",
      "choices": [
        "Microsoft 365",
        "Azure Virtual Machines",
        "Dynamics 365",
        "Azure DevOps"
      ],
      "answer": 1
    },
    "exam": {
      "question": "IaaSに関する記述として、正しいものはどれか。",
      "choices": [
        "利用者はハードウェアの管理が不要だがOSの管理は必要である",
        "利用者はアプリケーションのみ管理する",
        "プロバイダーがOSのパッチを適用する",
        "利用者はデータセンターの物理セキュリティを管理する"
      ],
      "answer": 0
    },
    "explanation": "IaaSでは物理インフラはプロバイダーが管理するが、OS、ミドルウェア、アプリケーション、データは利用者が管理する。仮想マシンの柔軟性と引き換えに管理責任が大きい。"
  },
  {
    "id": 21,
    "category": "クラウドの概念",
    "basic": {
      "question": "クラウドの「予測可能性」が指すものはどれか。",
      "choices": [
        "天気予報ができること",
        "パフォーマンスとコストの予測が可能であること",
        "障害が予測できること",
        "ユーザー数が予測できること"
      ],
      "answer": 1
    },
    "exam": {
      "question": "クラウドのコスト予測可能性に関する記述として、正しいものはどれか。",
      "choices": [
        "クラウドのコストは予測できない",
        "料金計算ツールやコスト分析により事前にコストを見積もれる",
        "従量課金制ではコスト管理ができない",
        "予算アラートの設定はできない"
      ],
      "answer": 1
    },
    "explanation": "Azureでは料金計算ツール（Pricing Calculator）、TCO計算ツール、Cost Managementにより、コストの見積もり・監視・予算管理が可能で、予測可能性を高められる。"
  },
  {
    "id": 22,
    "category": "クラウドの概念",
    "basic": {
      "question": "消費ベースモデルの特徴はどれか。",
      "choices": [
        "使用しなくても料金が発生する",
        "使用したリソースに対してのみ支払う",
        "年間契約が必須",
        "返金制度がない"
      ],
      "answer": 1
    },
    "exam": {
      "question": "消費ベースモデルの利点として、正しくないものはどれか。",
      "choices": [
        "初期費用を抑えられる",
        "需要変動に対応しやすい",
        "使っていないリソースのコストを削減できる",
        "使用量に関わらず常に定額で支払える"
      ],
      "answer": 3
    },
    "explanation": "消費ベースモデルは使用量に応じて料金が変動するため定額ではない。初期費用不要、需要変動への対応、未使用リソースのコスト削減が利点。"
  },
  {
    "id": 23,
    "category": "クラウドの概念",
    "basic": {
      "question": "「管理性」がクラウドの利点とされる理由はどれか。",
      "choices": [
        "管理が不要になるから",
        "テンプレートやAPIで効率的に管理できるから",
        "手動操作のみで管理するから",
        "管理者が不要になるから"
      ],
      "answer": 1
    },
    "exam": {
      "question": "クラウドの管理性に関する記述として、正しいものはどれか。",
      "choices": [
        "クラウドリソースはGUIでしか管理できない",
        "ARM テンプレート等でインフラをコードとして管理（IaC）できる",
        "クラウドでは自動化は実現できない",
        "すべてのリソースは手動で個別に設定する必要がある"
      ],
      "answer": 1
    },
    "explanation": "クラウドではARM テンプレート、Terraform等のIaC（Infrastructure as Code）ツールでインフラを自動化・標準化して管理できる。GUI、CLI、APIなど多様な管理手段がある。"
  },
  {
    "id": 24,
    "category": "クラウドの概念",
    "basic": {
      "question": "サーバーレスコンピューティングの特徴はどれか。",
      "choices": [
        "物理サーバーが存在しない",
        "サーバー管理が不要でイベント駆動で実行される",
        "常時サーバーを稼働させる必要がある",
        "IaaSの一種である"
      ],
      "answer": 1
    },
    "exam": {
      "question": "サーバーレスに関する記述として、正しくないものはどれか。",
      "choices": [
        "インフラ管理をプロバイダーに完全に委任できる",
        "イベント発生時にのみコードが実行される",
        "実行時間に対してのみ課金される",
        "利用者がOSのパッチ管理を行う必要がある"
      ],
      "answer": 3
    },
    "explanation": "サーバーレスでは利用者はOSの管理を一切行わない。プロバイダーがすべてのインフラを管理し、利用者はコードの実行にのみ集中する。Azure Functionsが代表例。"
  },
  {
    "id": 25,
    "category": "クラウドの概念",
    "basic": {
      "question": "TCO（総所有コスト）とは何か。",
      "choices": [
        "月額の利用料のみ",
        "購入から運用・廃棄までの全コスト",
        "初期購入費用のみ",
        "人件費のみ"
      ],
      "answer": 1
    },
    "exam": {
      "question": "TCOの比較においてクラウドが有利になる要因として、正しいものはどれか。",
      "choices": [
        "クラウドではハードウェアの保守費用が利用者に発生しない",
        "クラウドではデータセンターの電気代を利用者が負担する",
        "オンプレミスの方が常にTCOが低い",
        "クラウドでは人件費が増加する"
      ],
      "answer": 0
    },
    "explanation": "TCOはハードウェア、ソフトウェア、運用、電気代、施設費、人件費等を含む総コスト。クラウドではこれらの多くがプロバイダー負担となり、利用者のTCOを削減できる場合が多い。"
  },
  {
    "id": 26,
    "category": "クラウドの概念",
    "basic": {
      "question": "クラウドの「セキュリティ」に関する正しい記述はどれか。",
      "choices": [
        "クラウドはオンプレミスより常に安全でない",
        "クラウドプロバイダーは物理セキュリティに多額の投資をしている",
        "セキュリティはすべて利用者の責任",
        "クラウドでは暗号化ができない"
      ],
      "answer": 1
    },
    "exam": {
      "question": "クラウドセキュリティに関する記述として、正しいものの組合せはどれか。\n\nA. プロバイダーは物理データセンターのセキュリティを担保する\nB. 利用者はデータの暗号化やアクセス管理に責任を持つ\nC. クラウドではセキュリティは完全にプロバイダー任せでよい\nD. 共有責任モデルは適用されない",
      "choices": [
        "AとB",
        "AとC",
        "BとD",
        "CとD"
      ],
      "answer": 0
    },
    "explanation": "クラウドセキュリティは共有責任。プロバイダーは物理インフラを保護し、利用者はデータ、ID、アクセス管理等を担当する。完全にプロバイダー任せにはできない。"
  },
  {
    "id": 27,
    "category": "クラウドの概念",
    "basic": {
      "question": "クラウドへの移行パターンで「リフト＆シフト」とは何か。",
      "choices": [
        "アプリを一から作り直す",
        "既存のアプリをそのままクラウドに移行する",
        "クラウドからオンプレミスに戻す",
        "アプリを廃止する"
      ],
      "answer": 1
    },
    "exam": {
      "question": "クラウド移行に関する記述として、正しいものはどれか。",
      "choices": [
        "リフト＆シフトではアプリのコード変更が必須である",
        "リフト＆シフトは最小限の変更で既存アプリをクラウドに移行する方法である",
        "すべてのアプリはPaaSに移行すべきである",
        "クラウド移行は常に短期間で完了する"
      ],
      "answer": 1
    },
    "explanation": "リフト＆シフトは既存のアプリケーションを最小限の変更でクラウド（主にIaaS）に移行する方法。迅速な移行が可能だが、クラウドネイティブの利点を最大限活用するにはリファクタリングが必要になる場合もある。"
  },
  {
    "id": 28,
    "category": "クラウドの概念",
    "basic": {
      "question": "クラウドで「冗長性」が重要な理由はどれか。",
      "choices": [
        "コストを増やすため",
        "障害時にもサービスを継続するため",
        "管理を複雑にするため",
        "速度を下げるため"
      ],
      "answer": 1
    },
    "exam": {
      "question": "冗長性に関する記述として、正しくないものはどれか。",
      "choices": [
        "データを複数の場所にレプリケートすることで耐障害性が向上する",
        "可用性ゾーンは冗長性の実現に有効である",
        "冗長構成はSLAの向上に寄与する",
        "冗長構成にすると可用性が低下する"
      ],
      "answer": 3
    },
    "explanation": "冗長構成（レプリケーション、可用性ゾーン、リージョンペア等）はサービスの可用性とSLAを向上させる。単一障害点を排除し、障害時のサービス継続を実現する。"
  },
  {
    "id": 29,
    "category": "クラウドの概念",
    "basic": {
      "question": "Azure Well-Architected Frameworkの柱に含まれないものはどれか。",
      "choices": [
        "信頼性",
        "セキュリティ",
        "マーケティング",
        "コスト最適化"
      ],
      "answer": 2
    },
    "exam": {
      "question": "Azure Well-Architected Frameworkに関する記述として、正しいものはどれか。",
      "choices": [
        "5つの柱：信頼性、セキュリティ、コスト最適化、オペレーショナルエクセレンス、パフォーマンス効率で構成される",
        "コスト最適化は含まれない",
        "セキュリティは対象外である",
        "3つの柱で構成される"
      ],
      "answer": 0
    },
    "explanation": "Azure Well-Architected Frameworkは5つの柱（信頼性、セキュリティ、コスト最適化、オペレーショナルエクセレンス、パフォーマンス効率）で優れたクラウドアーキテクチャの指針を提供する。"
  },
  {
    "id": 30,
    "category": "クラウドの概念",
    "basic": {
      "question": "クラウドサービスの「可用性」を示す指標はどれか。",
      "choices": [
        "CPU使用率",
        "稼働率（アップタイム）",
        "ディスク容量",
        "ネットワーク帯域"
      ],
      "answer": 1
    },
    "exam": {
      "question": "SLA 99.9%の場合、1ヶ月あたりの許容ダウンタイムとして最も近いものはどれか。",
      "choices": [
        "約44分",
        "約4.4分",
        "約8.8時間",
        "約0秒"
      ],
      "answer": 0
    },
    "explanation": "SLA 99.9%は1ヶ月（約730時間）あたり約44分のダウンタイムが許容される。99.99%なら約4.4分。SLAの数字が上がるほど許容ダウンタイムは短くなり、実現コストも上がる。"
  },
  {
    "id": 31,
    "category": "クラウドの概念",
    "basic": {
      "question": "クラウドの利点「グローバルリーチ」とは何か。",
      "choices": [
        "1つの国でのみ利用可能",
        "世界中のリージョンにリソースをデプロイできる",
        "ローカルネットワークのみ利用可能",
        "特定のデバイスでのみアクセス可能"
      ],
      "answer": 1
    },
    "exam": {
      "question": "グローバルリーチに関する記述として、正しくないものはどれか。",
      "choices": [
        "世界中のリージョンにリソースを展開できる",
        "ユーザーに最も近いリージョンからサービスを提供しレイテンシを最小化できる",
        "データ主権の要件に対応するために特定のリージョンを選択できる",
        "Azureは世界に1つのリージョンしかない"
      ],
      "answer": 3
    },
    "explanation": "Azureは60以上のリージョンを世界中に持ち、グローバルにサービスを展開できる。ユーザーに近いリージョンを選ぶことでレイテンシを最小化し、各国のデータ規制にも対応できる。"
  },
  {
    "id": 32,
    "category": "クラウドの概念",
    "basic": {
      "question": "クラウドの利点で「フォールトトレランス」とは何か。",
      "choices": [
        "障害が絶対に起きないこと",
        "障害が発生してもシステムが動作し続ける能力",
        "障害を手動で復旧すること",
        "障害の原因を調査すること"
      ],
      "answer": 1
    },
    "exam": {
      "question": "フォールトトレランスに関する記述として、正しいものはどれか。",
      "choices": [
        "フォールトトレランスは障害を完全に防止することを指す",
        "冗長化やレプリケーションにより障害時もサービスを継続する能力を指す",
        "単一コンポーネントで実現できる",
        "バックアップとフォールトトレランスは同じ概念である"
      ],
      "answer": 1
    },
    "explanation": "フォールトトレランスは障害が発生してもシステムが動作し続ける能力。冗長化、レプリケーション、自動フェイルオーバー等の仕組みで実現する。障害防止ではなく障害耐性の概念。"
  },
  {
    "id": 33,
    "category": "クラウドの概念",
    "basic": {
      "question": "「デプロイモデル」として正しくないものはどれか。",
      "choices": [
        "パブリッククラウド",
        "プライベートクラウド",
        "ハイブリッドクラウド",
        "ローカルクラウド"
      ],
      "answer": 3
    },
    "exam": {
      "question": "クラウドデプロイモデルの選択に関する記述として、正しいものはどれか。",
      "choices": [
        "すべての組織はパブリッククラウドのみを使うべきである",
        "規制要件やレガシーシステムの都合でハイブリッドクラウドが選択されることがある",
        "プライベートクラウドはスケーラビリティが最も高い",
        "デプロイモデルの選択はセキュリティに影響しない"
      ],
      "answer": 1
    },
    "explanation": "デプロイモデルの選択は組織の要件次第。規制要件（データ国内保持等）やレガシーシステムの移行制約がある場合、ハイブリッドクラウドが適切な選択になることが多い。"
  },
  {
    "id": 34,
    "category": "クラウドの概念",
    "basic": {
      "question": "クラウドにおける「スケールイン」とは何か。",
      "choices": [
        "リソースの数を増やすこと",
        "リソースの数を減らすこと",
        "リソースの性能を上げること",
        "リソースを別リージョンに移動すること"
      ],
      "answer": 1
    },
    "exam": {
      "question": "スケーリングの用語に関する記述として、正しいものはどれか。",
      "choices": [
        "スケールアウトはリソース数を減らすことである",
        "スケールインはリソース数を減らすことである",
        "スケールアップはリソース数を増やすことである",
        "スケールダウンはリソース数を増やすことである"
      ],
      "answer": 1
    },
    "explanation": "スケールアウト＝リソース数を増やす、スケールイン＝リソース数を減らす。スケールアップ＝性能を上げる、スケールダウン＝性能を下げる。水平がアウト/イン、垂直がアップ/ダウン。"
  },
  {
    "id": 35,
    "category": "クラウドの概念",
    "basic": {
      "question": "コミュニティクラウドとは何か。",
      "choices": [
        "一般公開されたクラウド",
        "共通の関心を持つ複数の組織で共有するクラウド",
        "個人専用のクラウド",
        "無料のクラウドサービス"
      ],
      "answer": 1
    },
    "exam": {
      "question": "クラウドのデプロイモデルに関する記述として、正しくないものはどれか。",
      "choices": [
        "パブリッククラウドは誰でも利用できるクラウドサービスである",
        "プライベートクラウドは特定の組織専用に運用される",
        "ハイブリッドクラウドはパブリックとプライベートの組み合わせである",
        "パブリッククラウドはセキュリティが全く確保されていない"
      ],
      "answer": 3
    },
    "explanation": "パブリッククラウドは多数の利用者が共有するが、プロバイダーにより高度なセキュリティが確保されている。物理セキュリティ、暗号化、アクセス制御等が実装されている。"
  },
  {
    "id": 36,
    "category": "クラウドの概念",
    "basic": {
      "question": "クラウドの利点として「規模の経済」が挙げられる理由はどれか。",
      "choices": [
        "利用者が少ないため",
        "大規模運用によりコストを低減しその恩恵を利用者に還元できるため",
        "小規模運用だから",
        "プロバイダーが利益を得ないため"
      ],
      "answer": 1
    },
    "exam": {
      "question": "クラウドの規模の経済に関する記述として、正しいものはどれか。",
      "choices": [
        "クラウドプロバイダーは大量のハードウェアを安価に調達し運用コストを下げられる",
        "規模の経済は利用者には還元されない",
        "小規模なデータセンターの方が効率的である",
        "規模の経済はオンプレミスでも同様に実現できる"
      ],
      "answer": 0
    },
    "explanation": "クラウドプロバイダーは巨大なスケールでハードウェアを調達・運用するため、1ユニットあたりのコストが低くなる。この規模の経済の恩恵が従量課金の安さとして利用者に還元される。"
  },
  {
    "id": 37,
    "category": "Azureのアーキテクチャとサービス",
    "basic": {
      "question": "Azure Virtual Machinesが該当するサービスモデルはどれか。",
      "choices": [
        "SaaS",
        "PaaS",
        "IaaS",
        "FaaS"
      ],
      "answer": 2
    },
    "exam": {
      "question": "Azure VMに関する記述として、正しいものはどれか。",
      "choices": [
        "OSのパッチ管理はAzureが行う",
        "利用者がOSの管理・パッチ適用を行う",
        "サーバーレスサービスである",
        "PaaSに分類される"
      ],
      "answer": 1
    },
    "explanation": "Azure VMはIaaSのため、OSの選択・管理・パッチ適用は利用者の責任。Azureは物理インフラを管理する。"
  },
  {
    "id": 38,
    "category": "Azureのアーキテクチャとサービス",
    "basic": {
      "question": "Azure App Serviceの用途はどれか。",
      "choices": [
        "仮想マシンの管理",
        "Webアプリのホスティング",
        "物理サーバーの購入",
        "ネットワーク監視"
      ],
      "answer": 1
    },
    "exam": {
      "question": "Azure App Serviceに関する記述として、正しくないものはどれか。",
      "choices": [
        "PaaSサービスである",
        "WebアプリやREST APIをホストできる",
        "自動スケーリングをサポートする",
        "利用者がOSのパッチ管理を行う"
      ],
      "answer": 3
    },
    "explanation": "Azure App ServiceはPaaSのため、OS管理・パッチ適用はAzureが自動で行う。利用者はアプリのデプロイに集中できる。"
  },
  {
    "id": 39,
    "category": "Azureのアーキテクチャとサービス",
    "basic": {
      "question": "Azure Blob Storageの主な用途はどれか。",
      "choices": [
        "リレーショナルDB",
        "非構造化データの保存",
        "仮想マシンの実行",
        "メール送信"
      ],
      "answer": 1
    },
    "exam": {
      "question": "Blob Storageのアクセス層で保存コストが最も低いものはどれか。",
      "choices": [
        "ホット層",
        "クール層",
        "アーカイブ層",
        "プレミアム層"
      ],
      "answer": 2
    },
    "explanation": "アーカイブ層は保存コストが最も低いがアクセスコストが最も高い。ホット層は頻繁アクセス向け、クール層は30日以上の低頻度アクセス向け。"
  },
  {
    "id": 40,
    "category": "Azureのアーキテクチャとサービス",
    "basic": {
      "question": "Azureのリージョンとは何か。",
      "choices": [
        "課金単位",
        "データセンターが配置された地理的場所",
        "ユーザーアカウントの種類",
        "ネットワーク速度"
      ],
      "answer": 1
    },
    "exam": {
      "question": "Azureリージョンに関する記述として、正しくないものはどれか。",
      "choices": [
        "1つ以上のデータセンターで構成される",
        "世界中に60以上ある",
        "リージョン選択はレイテンシに影響する",
        "全リージョンで全サービスが利用可能"
      ],
      "answer": 3
    },
    "explanation": "全リージョンで全サービスが利用できるわけではない。新サービスは特定リージョンから段階的に展開される。"
  },
  {
    "id": 41,
    "category": "Azureのアーキテクチャとサービス",
    "basic": {
      "question": "可用性ゾーンとは何か。",
      "choices": [
        "異なるリージョン間の接続",
        "同一リージョン内の物理的に分離されたDC",
        "VMの種類",
        "ストレージの種類"
      ],
      "answer": 1
    },
    "exam": {
      "question": "可用性ゾーンに関する記述として、正しいものはどれか。",
      "choices": [
        "電源・冷却・ネットワークが独立している",
        "全リージョンに必ず存在する",
        "単一のラックで構成される",
        "可用性ゾーン間の通信はできない"
      ],
      "answer": 0
    },
    "explanation": "可用性ゾーンは独立した電源・冷却・ネットワークを持つ物理的に分離されたDC群。1ゾーン障害時も他ゾーンで継続できる。"
  },
  {
    "id": 42,
    "category": "Azureのアーキテクチャとサービス",
    "basic": {
      "question": "Azure Virtual Networkの役割はどれか。",
      "choices": [
        "データ暗号化",
        "Azureリソース間の通信を可能にする",
        "課金管理",
        "ユーザー認証"
      ],
      "answer": 1
    },
    "exam": {
      "question": "VNetに関する記述として、正しくないものはどれか。",
      "choices": [
        "サブネットでネットワークを分割できる",
        "NSGでトラフィックをフィルタリングできる",
        "VNet間はピアリングで接続できる",
        "VNetは自動的に全リージョンに展開される"
      ],
      "answer": 3
    },
    "explanation": "VNetはリージョン単位のリソースで自動展開されない。異なるリージョンのVNet接続にはVNetピアリングやVPN Gatewayが必要。"
  },
  {
    "id": 43,
    "category": "Azureのアーキテクチャとサービス",
    "basic": {
      "question": "Azure Functionsの特徴はどれか。",
      "choices": [
        "常時稼働のVM",
        "イベント駆動のサーバーレス",
        "リレーショナルDB",
        "ストレージサービス"
      ],
      "answer": 1
    },
    "exam": {
      "question": "Azure Functionsに関する記述として、正しくないものはどれか。",
      "choices": [
        "イベントトリガーで実行される",
        "実行時間に対してのみ課金される",
        "OSの管理が利用者に必要",
        "多数のプログラミング言語をサポート"
      ],
      "answer": 2
    },
    "explanation": "Azure Functionsはサーバーレスのため、OS管理は不要。イベント駆動で実行され、実行時間と回数に対してのみ課金される。"
  },
  {
    "id": 44,
    "category": "Azureのアーキテクチャとサービス",
    "basic": {
      "question": "Azure SQL Databaseのサービスモデルはどれか。",
      "choices": [
        "IaaS",
        "PaaS",
        "SaaS",
        "オンプレミス"
      ],
      "answer": 1
    },
    "exam": {
      "question": "Azure SQL Databaseに関する記述として、正しいものはどれか。",
      "choices": [
        "利用者がOSパッチを管理する",
        "自動バックアップや高可用性が組み込まれている",
        "IaaSサービスである",
        "NoSQLデータベースである"
      ],
      "answer": 1
    },
    "explanation": "Azure SQL DatabaseはPaaSのマネージドRDB。自動バックアップ、自動パッチ、高可用性が組み込まれており、利用者はDB設計とデータ管理に集中できる。"
  },
  {
    "id": 45,
    "category": "Azureのアーキテクチャとサービス",
    "basic": {
      "question": "Azure Cosmos DBの特徴はどれか。",
      "choices": [
        "単一リージョン専用DB",
        "グローバル分散型NoSQLデータベース",
        "ファイルストレージ",
        "仮想マシンサービス"
      ],
      "answer": 1
    },
    "exam": {
      "question": "Azure Cosmos DBに関する記述として、正しくないものはどれか。",
      "choices": [
        "マルチリージョンレプリケーションをサポート",
        "複数のAPIモデル（SQL, MongoDB等）に対応",
        "1桁ミリ秒のレイテンシを保証",
        "リレーショナルデータベースである"
      ],
      "answer": 3
    },
    "explanation": "Cosmos DBはNoSQLのグローバル分散DB。SQL, MongoDB, Cassandra等のAPIをサポートし、99パーセンタイルで1桁msのレイテンシを保証する。"
  },
  {
    "id": 46,
    "category": "Azureのアーキテクチャとサービス",
    "basic": {
      "question": "Azure Container Instancesの用途はどれか。",
      "choices": [
        "物理サーバー管理",
        "コンテナをサーバーレスで実行",
        "メール送信",
        "DNS管理"
      ],
      "answer": 1
    },
    "exam": {
      "question": "コンテナサービスに関する記述として、正しいものはどれか。",
      "choices": [
        "ACI はVM上でOSを管理する必要がある",
        "AKSはKubernetesのマネージドサービスである",
        "コンテナはVMより起動が遅い",
        "コンテナではアプリの分離ができない"
      ],
      "answer": 1
    },
    "explanation": "AKS（Azure Kubernetes Service）はKubernetesのマネージドサービス。ACIはサーバーレスで単一コンテナを迅速に実行できる。コンテナはVMより軽量で起動が速い。"
  },
  {
    "id": 47,
    "category": "Azureのアーキテクチャとサービス",
    "basic": {
      "question": "リージョンペアの目的はどれか。",
      "choices": [
        "コスト削減",
        "災害時のフェイルオーバー先として機能",
        "ネットワーク高速化",
        "VM数の削減"
      ],
      "answer": 1
    },
    "exam": {
      "question": "リージョンペアに関する記述として、正しくないものはどれか。",
      "choices": [
        "同じ地域内の2つのリージョンがペアになる",
        "計画メンテナンス時は同時にアップデートされない",
        "片方の障害時にもう片方で継続できる",
        "リージョンペアは利用者が自由に変更できる"
      ],
      "answer": 3
    },
    "explanation": "リージョンペアはAzureが事前に定義したもので利用者が変更できない。同地域内300マイル以上離れた2リージョンがペアとなり、同時メンテナンスを避ける設計。"
  },
  {
    "id": 48,
    "category": "Azureのアーキテクチャとサービス",
    "basic": {
      "question": "Azure Load Balancerの役割はどれか。",
      "choices": [
        "データ暗号化",
        "トラフィックを複数のVMに分散",
        "ストレージ管理",
        "ID管理"
      ],
      "answer": 1
    },
    "exam": {
      "question": "負荷分散に関する記述として、正しいものはどれか。",
      "choices": [
        "Azure Load BalancerはL4（TCP/UDP）で動作する",
        "Application GatewayはL4で動作する",
        "Load Balancerはhttpヘッダーに基づくルーティングができる",
        "Traffic ManagerはDNSベースの負荷分散ではない"
      ],
      "answer": 0
    },
    "explanation": "Azure Load BalancerはL4（トランスポート層）で動作。Application GatewayはL7（アプリケーション層）でHTTPヘッダー等に基づくルーティングが可能。Traffic ManagerはDNSベースのグローバル負荷分散。"
  },
  {
    "id": 49,
    "category": "Azureのアーキテクチャとサービス",
    "basic": {
      "question": "Azure ExpressRouteとは何か。",
      "choices": [
        "パブリックインターネット経由の接続",
        "オンプレミスとAzure間の専用プライベート接続",
        "無料のVPNサービス",
        "メールサービス"
      ],
      "answer": 1
    },
    "exam": {
      "question": "ExpressRouteに関する記述として、正しくないものはどれか。",
      "choices": [
        "パブリックインターネットを経由しない",
        "帯域幅が保証される",
        "VPN Gatewayより高い信頼性を提供",
        "VPN Gatewayより常にコストが低い"
      ],
      "answer": 3
    },
    "explanation": "ExpressRouteはVPN Gatewayより高コストだが、パブリックインターネットを経由せず帯域保証・低レイテンシ・高信頼性を提供する専用接続。"
  },
  {
    "id": 50,
    "category": "Azureのアーキテクチャとサービス",
    "basic": {
      "question": "Azure Active Directory（Microsoft Entra ID）の主な機能はどれか。",
      "choices": [
        "ファイル保存",
        "ID管理と認証",
        "仮想マシン作成",
        "データベース管理"
      ],
      "answer": 1
    },
    "exam": {
      "question": "Microsoft Entra ID（旧Azure AD）に関する記述として、正しいものはどれか。",
      "choices": [
        "オンプレミスのActive Directoryと同じものである",
        "クラウドベースのID・アクセス管理サービスである",
        "ストレージサービスである",
        "ネットワーク監視サービスである"
      ],
      "answer": 1
    },
    "explanation": "Microsoft Entra ID（旧Azure AD）はクラウドベースのID管理サービス。シングルサインオン、多要素認証、条件付きアクセス等を提供。オンプレADとは異なるサービス。"
  },
  {
    "id": 51,
    "category": "Azureのアーキテクチャとサービス",
    "basic": {
      "question": "Azure Storage Accountで利用できないストレージサービスはどれか。",
      "choices": [
        "Blob Storage",
        "File Storage",
        "Table Storage",
        "Virtual Machine"
      ],
      "answer": 3
    },
    "exam": {
      "question": "Azure Storageに関する記述として、正しいものはどれか。",
      "choices": [
        "Azure Filesはsmbプロトコルでアクセスできるファイル共有",
        "Azure Blobはリレーショナルデータ用",
        "Table Storageは構造化クエリに最適化されたRDB",
        "Queue Storageは動画配信用"
      ],
      "answer": 0
    },
    "explanation": "Azure Filesはsmbプロトコルでアクセスできるフルマネージドのファイル共有。BlobはオブジェクトストレージTableはNoSQLキーバリュー、Queueはメッセージキューサービス。"
  },
  {
    "id": 52,
    "category": "Azureのアーキテクチャとサービス",
    "basic": {
      "question": "Azure VPN Gatewayの用途はどれか。",
      "choices": [
        "データベース管理",
        "オンプレミスとAzure間の暗号化された接続",
        "Webアプリホスティング",
        "メール送信"
      ],
      "answer": 1
    },
    "exam": {
      "question": "VPN接続に関する記述として、正しくないものはどれか。",
      "choices": [
        "サイト間VPNでオンプレミスとAzureを接続できる",
        "ポイント対サイトVPNで個別デバイスから接続できる",
        "VPN通信は暗号化される",
        "VPNはExpressRouteと同じく専用回線を使用する"
      ],
      "answer": 3
    },
    "explanation": "VPN Gatewayはパブリックインターネット上で暗号化されたトンネルを作る。ExpressRouteは専用回線。VPNはコストが低いが帯域保証がなくレイテンシが変動する。"
  },
  {
    "id": 53,
    "category": "Azureのアーキテクチャとサービス",
    "basic": {
      "question": "Azure CDN（Content Delivery Network）の目的はどれか。",
      "choices": [
        "データベースのバックアップ",
        "コンテンツをユーザーに近い場所からキャッシュ配信",
        "仮想マシンの管理",
        "ID認証"
      ],
      "answer": 1
    },
    "exam": {
      "question": "Azure CDNに関する記述として、正しいものはどれか。",
      "choices": [
        "動的コンテンツのみ配信できる",
        "世界中のPOP（エッジサーバー）にコンテンツをキャッシュしレイテンシを低減する",
        "オリジンサーバーの負荷が増加する",
        "1つのリージョンでのみ利用可能"
      ],
      "answer": 1
    },
    "explanation": "CDNは世界中に分散したエッジサーバー（POP）にコンテンツをキャッシュし、ユーザーに最も近い場所から配信することでレイテンシを低減しオリジンの負荷を軽減する。"
  },
  {
    "id": 54,
    "category": "Azureのアーキテクチャとサービス",
    "basic": {
      "question": "Azure DNSの機能はどれか。",
      "choices": [
        "仮想マシン作成",
        "ドメイン名の名前解決",
        "ファイル保存",
        "課金管理"
      ],
      "answer": 1
    },
    "exam": {
      "question": "Azure DNSに関する記述として、正しくないものはどれか。",
      "choices": [
        "DNSゾーンをAzure上でホストできる",
        "Azureの他サービスと統合した管理が可能",
        "RBACによるアクセス制御が可能",
        "ドメイン名の購入（登録）ができる"
      ],
      "answer": 3
    },
    "explanation": "Azure DNSはDNSゾーンのホスティングサービスだが、ドメイン名の購入（レジストラ機能）は提供しない。ドメインは別途レジストラで購入しAzure DNSに委任する。"
  },
  {
    "id": 55,
    "category": "Azureのアーキテクチャとサービス",
    "basic": {
      "question": "Azure Kubernetes Service（AKS）の用途はどれか。",
      "choices": [
        "メール送信",
        "コンテナオーケストレーション",
        "DNS管理",
        "ファイル共有"
      ],
      "answer": 1
    },
    "exam": {
      "question": "AKSに関する記述として、正しいものはどれか。",
      "choices": [
        "AKSではKubernetesのコントロールプレーンをAzureが管理する",
        "利用者がマスターノードの管理を行う",
        "VMベースのサービスでコンテナは使えない",
        "サーバーレスサービスである"
      ],
      "answer": 0
    },
    "explanation": "AKSはKubernetesのマネージドサービスで、コントロールプレーン（マスターノード）はAzureが管理。利用者はワーカーノードとアプリケーションの管理に集中する。"
  },
  {
    "id": 56,
    "category": "Azureのアーキテクチャとサービス",
    "basic": {
      "question": "Azure Firewallの役割はどれか。",
      "choices": [
        "データ保存",
        "ネットワークトラフィックの監視・フィルタリング",
        "VM作成",
        "ID管理"
      ],
      "answer": 1
    },
    "exam": {
      "question": "Azure Firewallに関する記述として、正しくないものはどれか。",
      "choices": [
        "フルステートフルなネットワークファイアウォール",
        "アプリケーションルールとネットワークルールを設定できる",
        "脅威インテリジェンスベースのフィルタリングが可能",
        "NSGと完全に同じ機能である"
      ],
      "answer": 3
    },
    "explanation": "Azure FirewallはNSGより高機能なマネージドファイアウォール。FQDN フィルタリング、脅威インテリジェンス、TLS検査等が可能。NSGはサブネット/NIC レベルのL3/L4フィルタリング。"
  },
  {
    "id": 57,
    "category": "Azureのアーキテクチャとサービス",
    "basic": {
      "question": "NSG（ネットワークセキュリティグループ）の機能はどれか。",
      "choices": [
        "課金管理",
        "受信・送信トラフィックのフィルタリングルール",
        "VM作成",
        "データベース管理"
      ],
      "answer": 1
    },
    "exam": {
      "question": "NSGに関する記述として、正しいものはどれか。",
      "choices": [
        "NSGはサブネットまたはNICにアタッチできる",
        "NSGはL7のアプリケーションフィルタリングができる",
        "NSGはDDoS攻撃を完全に防止する",
        "NSGは課金管理ツールである"
      ],
      "answer": 0
    },
    "explanation": "NSGはL3/L4レベルでIPアドレス、ポート、プロトコルに基づいてトラフィックをフィルタリングする。サブネットまたはNIC（ネットワークインターフェース）にアタッチする。"
  },
  {
    "id": 58,
    "category": "Azureのアーキテクチャとサービス",
    "basic": {
      "question": "Azure DevOpsの用途はどれか。",
      "choices": [
        "物理サーバー管理",
        "ソフトウェア開発のCI/CDパイプライン",
        "ハードウェア購入",
        "電源管理"
      ],
      "answer": 1
    },
    "exam": {
      "question": "Azure DevOpsに関する記述として、正しくないものはどれか。",
      "choices": [
        "リポジトリ管理、パイプライン、ボードを提供",
        "CI/CDの自動化を支援",
        "Agile開発のプロジェクト管理に利用できる",
        "仮想マシンのスペック管理専用ツールである"
      ],
      "answer": 3
    },
    "explanation": "Azure DevOpsはソフトウェア開発のためのサービス群（Repos, Pipelines, Boards, Artifacts, Test Plans）を提供。CI/CDの自動化やAgileプロジェクト管理に使用する。"
  },
  {
    "id": 59,
    "category": "Azureのアーキテクチャとサービス",
    "basic": {
      "question": "Azure IoT Hubの用途はどれか。",
      "choices": [
        "Webサイトホスティング",
        "IoTデバイスとクラウド間の通信管理",
        "メール送信",
        "ドメイン登録"
      ],
      "answer": 1
    },
    "exam": {
      "question": "Azure IoTサービスに関する記述として、正しいものはどれか。",
      "choices": [
        "IoT Hubはデバイスからクラウドへの一方向通信のみ可能",
        "IoT Hubは双方向通信をサポートする",
        "IoT CentralはIaaSサービスである",
        "IoTサービスはAzureでは提供されていない"
      ],
      "answer": 1
    },
    "explanation": "Azure IoT Hubはデバイス←→クラウドの双方向通信をサポートするメッセージングハブ。IoT Centralはマネージドのアプリケーションプラットフォームで迅速なIoTソリューション構築が可能。"
  },
  {
    "id": 60,
    "category": "Azureのアーキテクチャとサービス",
    "basic": {
      "question": "Azure Cognitive Servicesの用途はどれか。",
      "choices": [
        "VM管理",
        "AIの視覚・音声・言語・意思決定機能をAPIで提供",
        "ネットワーク管理",
        "課金管理"
      ],
      "answer": 1
    },
    "exam": {
      "question": "Azure AI サービスに関する記述として、正しくないものはどれか。",
      "choices": [
        "事前構築されたAIモデルをAPIで利用できる",
        "画像認識・音声認識・自然言語処理等が含まれる",
        "機械学習の専門知識なしでもAI機能を組み込める",
        "利用には必ず独自のMLモデルをトレーニングする必要がある"
      ],
      "answer": 3
    },
    "explanation": "Azure AI Services（旧Cognitive Services）は事前構築済みのAIモデルをAPIで提供。専門知識なしでもアプリにAI機能（画像認識、翻訳、感情分析等）を組み込める。"
  },
  {
    "id": 61,
    "category": "Azureのアーキテクチャとサービス",
    "basic": {
      "question": "Azure Machine Learningの用途はどれか。",
      "choices": [
        "ファイル共有",
        "機械学習モデルの構築・訓練・デプロイ",
        "DNS管理",
        "VPN接続"
      ],
      "answer": 1
    },
    "exam": {
      "question": "Azure Machine Learningに関する記述として、正しいものはどれか。",
      "choices": [
        "コードなしでは利用できない",
        "AutoMLで自動的に最適なモデルを選択できる",
        "ストレージサービスである",
        "ネットワーク監視ツールである"
      ],
      "answer": 1
    },
    "explanation": "Azure Machine LearningはMLモデルのライフサイクル全体を管理するプラットフォーム。AutoML機能でコードなしでも最適なアルゴリズムを自動選択・トレーニングできる。"
  },
  {
    "id": 62,
    "category": "Azureのアーキテクチャとサービス",
    "basic": {
      "question": "Azure Virtual Desktop（旧WVD）の用途はどれか。",
      "choices": [
        "物理PC購入",
        "クラウド上の仮想デスクトップ環境の提供",
        "メール送信",
        "DNS管理"
      ],
      "answer": 1
    },
    "exam": {
      "question": "Azure Virtual Desktopに関する記述として、正しくないものはどれか。",
      "choices": [
        "クラウドでホストされるデスクトップ仮想化サービス",
        "Windows 10/11のマルチセッションをサポート",
        "任意のデバイスからアクセス可能",
        "利用者が物理PCを管理する必要がある"
      ],
      "answer": 3
    },
    "explanation": "Azure Virtual Desktopはクラウドホストの仮想デスクトップ。物理PCの管理は不要で、任意のデバイスからセキュアにアクセスできる。Windows のマルチセッション対応。"
  },
  {
    "id": 63,
    "category": "Azureのアーキテクチャとサービス",
    "basic": {
      "question": "データの冗長性オプションでLRSとは何か。",
      "choices": [
        "ローカル冗長ストレージ（同一DC内3コピー）",
        "地理冗長ストレージ",
        "ゾーン冗長ストレージ",
        "読み取りアクセス地理冗長"
      ],
      "answer": 0
    },
    "exam": {
      "question": "ストレージ冗長性に関する記述として、正しいものはどれか。",
      "choices": [
        "LRSは同一データセンター内に3つのコピーを保持する",
        "ZRSは同一ゾーン内のみにデータを保存する",
        "GRSはセカンダリリージョンのデータに常時読み取りアクセスできる",
        "RA-GRSはプライマリリージョンのみ読み取り可能"
      ],
      "answer": 0
    },
    "explanation": "LRS:同一DC内3コピー、ZRS:同一リージョンの3ゾーンに分散、GRS:ペアリージョンにもコピー（読み取り不可）、RA-GRS:ペアリージョンのデータも読み取り可能。"
  },
  {
    "id": 64,
    "category": "Azureのアーキテクチャとサービス",
    "basic": {
      "question": "Azure Database for PostgreSQL/MySQLのサービスモデルはどれか。",
      "choices": [
        "IaaS",
        "PaaS",
        "SaaS",
        "オンプレミス"
      ],
      "answer": 1
    },
    "exam": {
      "question": "Azureのマネージドデータベースに関する記述として、正しくないものはどれか。",
      "choices": [
        "自動バックアップが含まれる",
        "高可用性が組み込まれている",
        "OSレベルのアクセスが可能である",
        "自動パッチ適用が行われる"
      ],
      "answer": 2
    },
    "explanation": "PaaSのマネージドDBではOSレベルのアクセスは提供されない。自動バックアップ、高可用性、自動パッチが含まれ、利用者はDB設計とデータ管理に集中する。"
  },
  {
    "id": 65,
    "category": "Azureのアーキテクチャとサービス",
    "basic": {
      "question": "Azure Data Lakeの用途はどれか。",
      "choices": [
        "メール送信",
        "大規模データの分析用ストレージ",
        "VMの作成",
        "DNS管理"
      ],
      "answer": 1
    },
    "exam": {
      "question": "ビッグデータ・分析サービスに関する記述として、正しいものはどれか。",
      "choices": [
        "Azure Synapse Analyticsは大規模データ分析サービスである",
        "Azure Data LakeはリレーショナルDB専用",
        "HDInsightはID管理サービスである",
        "Azure Databricksはストレージサービスである"
      ],
      "answer": 0
    },
    "explanation": "Azure Synapse Analytics（旧SQL Data Warehouse）は大規模データのクエリと分析を統合するサービス。Data Lakeは構造化・非構造化データの大規模保存、DatabricksはApache Sparkベースの分析プラットフォーム。"
  },
  {
    "id": 66,
    "category": "Azureのアーキテクチャとサービス",
    "basic": {
      "question": "Azure Marketplaceとは何か。",
      "choices": [
        "物理製品の販売サイト",
        "サードパーティ製ソリューションのカタログ",
        "Azureの課金ページ",
        "ソースコードリポジトリ"
      ],
      "answer": 1
    },
    "exam": {
      "question": "Azure Marketplaceに関する記述として、正しくないものはどれか。",
      "choices": [
        "サードパーティのアプリやサービスを検索・デプロイできる",
        "VM イメージ、SaaSアプリ、テンプレートが含まれる",
        "Microsoft認定パートナーが提供",
        "Azure以外のクラウドでしか使えない"
      ],
      "answer": 3
    },
    "explanation": "Azure MarketplaceはAzure上で利用できるサードパーティ製・Microsoft製のソリューションカタログ。VM イメージ、SaaSアプリ、ARMテンプレート等が提供される。"
  },
  {
    "id": 67,
    "category": "Azureのアーキテクチャとサービス",
    "basic": {
      "question": "Azure Resource Manager（ARM）の役割はどれか。",
      "choices": [
        "メール送信",
        "Azureリソースのデプロイ・管理レイヤー",
        "物理サーバー管理",
        "ドメイン購入"
      ],
      "answer": 1
    },
    "exam": {
      "question": "ARMに関する記述として、正しいものはどれか。",
      "choices": [
        "ARMはAzureの管理レイヤーで、すべてのリソース操作はARMを通じて行われる",
        "ARMはストレージサービスである",
        "ARMはポータルからのみアクセスできる",
        "ARMはネットワーク監視ツールである"
      ],
      "answer": 0
    },
    "explanation": "ARM（Azure Resource Manager）はすべてのAzureリソース操作の管理レイヤー。ポータル、CLI、PowerShell、SDK等すべてのリクエストはARMを通じて処理される。"
  },
  {
    "id": 68,
    "category": "Azureのアーキテクチャとサービス",
    "basic": {
      "question": "リソースグループとは何か。",
      "choices": [
        "課金プランの種類",
        "関連するAzureリソースをまとめる論理コンテナ",
        "物理サーバーの集合",
        "ネットワークの種類"
      ],
      "answer": 1
    },
    "exam": {
      "question": "リソースグループに関する記述として、正しくないものはどれか。",
      "choices": [
        "リソースは必ず1つのリソースグループに属する",
        "リソースグループを削除すると中のリソースも削除される",
        "RBACをリソースグループ単位で適用できる",
        "1つのリソースが複数のリソースグループに属することができる"
      ],
      "answer": 3
    },
    "explanation": "Azureリソースは必ず1つのリソースグループにのみ属する（複数不可）。リソースグループ削除時は中の全リソースが削除される。RBACやタグの管理単位として使われる。"
  },
  {
    "id": 69,
    "category": "Azureのアーキテクチャとサービス",
    "basic": {
      "question": "Azure DDoS Protectionの役割はどれか。",
      "choices": [
        "データバックアップ",
        "分散型サービス妨害攻撃からの保護",
        "ID管理",
        "課金管理"
      ],
      "answer": 1
    },
    "exam": {
      "question": "DDoS Protectionに関する記述として、正しいものはどれか。",
      "choices": [
        "BasicはすべてのAzureサービスに自動的に適用される",
        "Standardは無料で追加コストなし",
        "DDoS攻撃はAzureでは発生しない",
        "DDoS ProtectionはVMのサイズを変更する"
      ],
      "answer": 0
    },
    "explanation": "Azure DDoS Protection Basicは全Azureサービスに自動適用（無料）。StandardはVNet対象で高度な軽減・アラート・レポートを提供するが追加料金がかかる。"
  },
  {
    "id": 70,
    "category": "Azureのアーキテクチャとサービス",
    "basic": {
      "question": "サブスクリプションとは何か。",
      "choices": [
        "物理サーバー",
        "Azureサービスの利用契約・課金単位",
        "プログラミング言語",
        "ネットワーク機器"
      ],
      "answer": 1
    },
    "exam": {
      "question": "Azureサブスクリプションに関する記述として、正しくないものはどれか。",
      "choices": [
        "リソースの課金境界として機能する",
        "アクセス制御の境界として機能する",
        "1つのアカウントで複数のサブスクリプションを持てる",
        "サブスクリプションなしでもリソースを作成できる"
      ],
      "answer": 3
    },
    "explanation": "Azureリソースの作成にはサブスクリプションが必須。サブスクリプションは課金境界とアクセス制御境界の両方として機能し、1アカウントで複数持つことが可能。"
  },
  {
    "id": 71,
    "category": "Azureのアーキテクチャとサービス",
    "basic": {
      "question": "Azure Key Vaultの用途はどれか。",
      "choices": [
        "仮想マシン作成",
        "シークレット・キー・証明書の安全な管理",
        "ファイル共有",
        "ドメイン管理"
      ],
      "answer": 1
    },
    "exam": {
      "question": "Azure Key Vaultに関する記述として、正しいものはどれか。",
      "choices": [
        "パスワードやAPIキーを平文でストレージに保存するサービス",
        "暗号化キー、シークレット、証明書をセキュアに集中管理できる",
        "ネットワーク監視サービスである",
        "無料のVMサービスである"
      ],
      "answer": 1
    },
    "explanation": "Azure Key Vaultは暗号化キー、シークレット（パスワード、接続文字列等）、証明書をHSMで保護し集中管理するサービス。アプリからAPIでセキュアにアクセスする。"
  },
  {
    "id": 72,
    "category": "Azureのアーキテクチャとサービス",
    "basic": {
      "question": "Azure Monitorの用途はどれか。",
      "choices": [
        "ID管理",
        "Azureリソースのメトリクスとログの収集・分析",
        "VM作成",
        "ドメイン購入"
      ],
      "answer": 1
    },
    "exam": {
      "question": "Azure Monitorに関する記述として、正しくないものはどれか。",
      "choices": [
        "メトリクスとログを収集・分析する",
        "アラートを設定して通知できる",
        "ダッシュボードで可視化できる",
        "リソースの作成・削除を行うサービスである"
      ],
      "answer": 3
    },
    "explanation": "Azure Monitorはリソースのパフォーマンスメトリクスとログを収集・分析・可視化するサービス。アラート設定や自動アクション（スケーリング等）も可能。リソース操作はARM。"
  },
  {
    "id": 73,
    "category": "Azureのアーキテクチャとサービス",
    "basic": {
      "question": "Azure Application Gatewayの役割はどれか。",
      "choices": [
        "ストレージ管理",
        "L7ロードバランサー（Webトラフィックの負荷分散）",
        "ID管理",
        "課金管理"
      ],
      "answer": 1
    },
    "exam": {
      "question": "Application GatewayとLoad Balancerの違いとして正しいものはどれか。",
      "choices": [
        "Application GatewayはL4で動作する",
        "Load BalancerはURLパスベースのルーティングができる",
        "Application GatewayはL7でHTTPヘッダーやURLに基づくルーティングが可能",
        "両者に機能的な違いはない"
      ],
      "answer": 2
    },
    "explanation": "Application GatewayはL7ロードバランサーで、URLパス、ホスト名、HTTPヘッダーに基づくルーティング、WAF（Web Application Firewall）機能を提供。Load BalancerはL4でIP/ポートベース。"
  },
  {
    "id": 74,
    "category": "Azureのアーキテクチャとサービス",
    "basic": {
      "question": "Azure Front Doorの用途はどれか。",
      "choices": [
        "データベース管理",
        "グローバルなWebアプリの高速化・負荷分散・WAF",
        "VM管理",
        "ストレージ"
      ],
      "answer": 1
    },
    "exam": {
      "question": "Azure Front Doorに関する記述として、正しいものはどれか。",
      "choices": [
        "リージョン内のみで動作する",
        "グローバルなL7ロードバランサーでCDN・WAF機能も統合されている",
        "DNSサービスの代替である",
        "オンプレミス専用サービスである"
      ],
      "answer": 1
    },
    "explanation": "Azure Front DoorはグローバルなL7ロードバランサーで、CDN、WAF、SSL終端を統合。世界中のエッジロケーションからトラフィックを最適にルーティングする。"
  },
  {
    "id": 75,
    "category": "Azureのアーキテクチャとサービス",
    "basic": {
      "question": "Azure Logic Appsの用途はどれか。",
      "choices": [
        "物理サーバー管理",
        "コードなしでワークフローを自動化",
        "データベース作成",
        "ドメイン登録"
      ],
      "answer": 1
    },
    "exam": {
      "question": "Azure Logic Appsに関する記述として、正しくないものはどれか。",
      "choices": [
        "ビジュアルデザイナーでワークフローを構築できる",
        "数百のコネクタで外部サービスと連携できる",
        "サーバーレスで実行される",
        "利用には必ずC#のコーディングが必要"
      ],
      "answer": 3
    },
    "explanation": "Logic Appsはローコード/ノーコードのワークフロー自動化サービス。ビジュアルデザイナーと豊富なコネクタでコーディング不要でビジネスプロセスを自動化できる。"
  },
  {
    "id": 76,
    "category": "Azureのアーキテクチャとサービス",
    "basic": {
      "question": "Azure Service Busの用途はどれか。",
      "choices": [
        "VM作成",
        "アプリケーション間のメッセージング",
        "ファイル共有",
        "ドメイン管理"
      ],
      "answer": 1
    },
    "exam": {
      "question": "メッセージングサービスに関する記述として、正しいものはどれか。",
      "choices": [
        "Service Busはシンプルなキューのみサポートする",
        "Service BusはキューとトピックによるPub/Subパターンをサポートする",
        "Event Hubsはリレーショナルデータベースである",
        "Event Gridはファイルストレージである"
      ],
      "answer": 1
    },
    "exam_note": "",
    "explanation": "Service Busはエンタープライズ級のメッセージブローカー。キュー（1対1）とトピック（Pub/Sub）をサポート。Event Hubsはビッグデータストリーミング、Event Gridはイベントルーティング。"
  },
  {
    "id": 77,
    "category": "Azureのアーキテクチャとサービス",
    "basic": {
      "question": "Azure Notification Hubsの用途はどれか。",
      "choices": [
        "データベース管理",
        "モバイルデバイスへのプッシュ通知",
        "VM管理",
        "VPN接続"
      ],
      "answer": 1
    },
    "exam": {
      "question": "Azure通信サービスに関する記述として、正しくないものはどれか。",
      "choices": [
        "Notification Hubsはモバイルプッシュ通知を大規模に配信する",
        "Azure Communication Servicesは音声・ビデオ・チャットを提供する",
        "SignalRはリアルタイムWebアプリに使用される",
        "Notification Hubsはリレーショナルデータベースサービスである"
      ],
      "answer": 3
    },
    "explanation": "Azure Notification Hubsはモバイルアプリへのプッシュ通知を数百万デバイスに配信するサービス。Communication Servicesは音声/ビデオ通話、SignalRはリアルタイム通信。"
  },
  {
    "id": 78,
    "category": "Azureのアーキテクチャとサービス",
    "basic": {
      "question": "マネージドディスクとは何か。",
      "choices": [
        "利用者がディスクの物理管理を行う",
        "Azureが管理するVM用ディスクストレージ",
        "USBディスク",
        "ネットワーク機器"
      ],
      "answer": 1
    },
    "exam": {
      "question": "Azure Managed Disksに関する記述として、正しいものはどれか。",
      "choices": [
        "利用者がストレージアカウントの容量計画を行う必要がある",
        "Azureがディスクの冗長性と可用性を管理する",
        "アンマネージドディスクと機能は同じ",
        "SSDは選択できない"
      ],
      "answer": 1
    },
    "explanation": "Managed DisksはAzureが管理するブロックストレージ。利用者はストレージアカウントの管理不要で、可用性・冗長性・暗号化をAzureが担保。SSD/HDDの選択が可能。"
  },
  {
    "id": 79,
    "category": "Azureのアーキテクチャとサービス",
    "basic": {
      "question": "Azure Bastion の用途はどれか。",
      "choices": [
        "データベース管理",
        "パブリックIPなしでVMにセキュアにRDP/SSH接続",
        "ファイル共有",
        "CDN"
      ],
      "answer": 1
    },
    "exam": {
      "question": "Azure Bastionに関する記述として、正しくないものはどれか。",
      "choices": [
        "Azure Portal経由でブラウザからVMに接続できる",
        "VMにパブリックIPを割り当てる必要がない",
        "RDPやSSHのポートをインターネットに公開せずに済む",
        "Bastionを使うにはVMにパブリックIPが必須である"
      ],
      "answer": 3
    },
    "explanation": "Azure BastionはVMにパブリックIPを付与せず、Azure Portal経由でブラウザからセキュアにRDP/SSH接続できるサービス。RDP/SSHポートの外部公開が不要。"
  },
  {
    "id": 80,
    "category": "Azureのアーキテクチャとサービス",
    "basic": {
      "question": "Azure Traffic Managerの役割はどれか。",
      "choices": [
        "VM管理",
        "DNSベースのグローバルトラフィック分散",
        "ストレージ管理",
        "ID認証"
      ],
      "answer": 1
    },
    "exam": {
      "question": "Traffic Managerに関する記述として、正しいものはどれか。",
      "choices": [
        "L7のHTTPロードバランサーである",
        "DNSレベルでトラフィックを最適なエンドポイントにルーティングする",
        "単一リージョンでのみ動作する",
        "Azure Firewallと同じ機能を持つ"
      ],
      "answer": 1
    },
    "explanation": "Traffic ManagerはDNSベースのグローバルトラフィック分散サービス。地理的近接性、パフォーマンス、優先度、重み付け等のルーティング方式を提供する。"
  },
  {
    "id": 81,
    "category": "Azureのアーキテクチャとサービス",
    "basic": {
      "question": "Azure VM Scale Setsの機能はどれか。",
      "choices": [
        "手動でのみVMを追加",
        "同一構成のVMを自動的にスケールイン/アウト",
        "単一VMの性能向上",
        "ストレージ管理"
      ],
      "answer": 1
    },
    "exam": {
      "question": "VM Scale Setsに関する記述として、正しくないものはどれか。",
      "choices": [
        "負荷に応じてVM数を自動的に増減できる",
        "同一構成のVM群を管理する",
        "Load Balancerと組み合わせて使用できる",
        "VMごとに異なるOSをデプロイする機能である"
      ],
      "answer": 3
    },
    "explanation": "VM Scale Setsは同一構成のVMグループを自動スケーリングする機能。負荷に応じてVM数が増減し、ロードバランサーと連携してトラフィックを分散する。全VMは同一イメージ。"
  },
  {
    "id": 82,
    "category": "Azureのアーキテクチャとサービス",
    "basic": {
      "question": "Azure Private Linkの目的はどれか。",
      "choices": [
        "パブリックインターネット経由でアクセス",
        "AzureサービスへのプライベートVNet経由アクセス",
        "メール送信",
        "CDN配信"
      ],
      "answer": 1
    },
    "exam": {
      "question": "Private Linkに関する記述として、正しいものはどれか。",
      "choices": [
        "パブリックインターネットを経由してサービスにアクセスする",
        "VNet内のプライベートIPでAzureサービスにアクセスでき通信がMicrosoftバックボーン上に留まる",
        "VPN接続と同じ機能である",
        "無料のストレージサービスである"
      ],
      "answer": 1
    },
    "explanation": "Azure Private LinkはAzureサービスをVNet内のプライベートIPで公開し、パブリックインターネットを経由せずMicrosoftバックボーン上で安全にアクセスする仕組み。"
  },
  {
    "id": 83,
    "category": "Azureのアーキテクチャとサービス",
    "basic": {
      "question": "管理グループ（Management Group）の役割はどれか。",
      "choices": [
        "VMの管理",
        "複数のサブスクリプションを階層的に管理",
        "ストレージの管理",
        "ネットワーク監視"
      ],
      "answer": 1
    },
    "exam": {
      "question": "Azureの階層構造として正しい順序（上位→下位）はどれか。",
      "choices": [
        "リソースグループ→サブスクリプション→管理グループ",
        "管理グループ→サブスクリプション→リソースグループ→リソース",
        "サブスクリプション→管理グループ→リソース",
        "リソース→リソースグループ→管理グループ"
      ],
      "answer": 1
    },
    "explanation": "Azureの管理階層は上位から：管理グループ→サブスクリプション→リソースグループ→リソース。上位で設定したポリシーやRBACは下位に継承される。"
  },
  {
    "id": 84,
    "category": "Azureのアーキテクチャとサービス",
    "basic": {
      "question": "Azure Migrateの用途はどれか。",
      "choices": [
        "メール送信",
        "オンプレミスからAzureへの移行を評価・支援",
        "DNS管理",
        "CDN配信"
      ],
      "answer": 1
    },
    "exam": {
      "question": "Azure Migrateに関する記述として、正しくないものはどれか。",
      "choices": [
        "オンプレミス環境の評価を行える",
        "移行のコスト見積もりが可能",
        "サーバー、データベース、アプリの移行を支援",
        "移行後の運用監視専用ツールである"
      ],
      "answer": 3
    },
    "explanation": "Azure Migrateは移行前の評価（パフォーマンス分析、依存関係マッピング、コスト見積もり）と移行実行を支援する統合ハブ。運用監視はAzure Monitorの役割。"
  },
  {
    "id": 85,
    "category": "Azureのアーキテクチャとサービス",
    "basic": {
      "question": "Azure Arc の目的はどれか。",
      "choices": [
        "Azureリソースのみ管理",
        "オンプレミスやマルチクラウドのリソースもAzureで一元管理",
        "メール送信",
        "ストレージのみ管理"
      ],
      "answer": 1
    },
    "exam": {
      "question": "Azure Arcに関する記述として、正しいものはどれか。",
      "choices": [
        "Azure内のリソースのみ管理対象である",
        "オンプレミスやAWS/GCP上のサーバー・DBもAzureの管理プレーンで統合管理できる",
        "ストレージサービスである",
        "VM作成専用ツールである"
      ],
      "answer": 1
    },
    "explanation": "Azure ArcはAzure外（オンプレミス、他クラウド）のサーバー、Kubernetes、データサービスをAzureの管理プレーン（ARM）に接続し、ポリシーや監視を統合的に適用する。"
  },
  {
    "id": 86,
    "category": "Azureのアーキテクチャとサービス",
    "basic": {
      "question": "Azure Disk Storageで選択できるディスクタイプで最も高性能なものはどれか。",
      "choices": [
        "Standard HDD",
        "Standard SSD",
        "Premium SSD",
        "Ultra Disk"
      ],
      "answer": 3
    },
    "exam": {
      "question": "Azure Disk Storageに関する記述として、正しいものはどれか。",
      "choices": [
        "Ultra DiskはIOPSとスループットを個別に構成できる",
        "Standard HDDが最も高性能である",
        "Premium SSDはすべてのVMサイズで利用可能",
        "ディスクのサイズは変更できない"
      ],
      "answer": 0
    },
    "explanation": "Ultra DiskはIOPS・スループットを個別に動的構成でき最高性能。Premium SSD > Standard SSD > Standard HDDの順。Premium以上は対応VMサイズが限定される。"
  },
  {
    "id": 87,
    "category": "Azureのアーキテクチャとサービス",
    "basic": {
      "question": "Azure Event Gridの用途はどれか。",
      "choices": [
        "VM管理",
        "イベントベースのリアクティブプログラミング",
        "ファイル保存",
        "ID管理"
      ],
      "answer": 1
    },
    "exam": {
      "question": "Azureのイベント・メッセージサービスの使い分けとして正しいものはどれか。",
      "choices": [
        "Event Gridはリッチなメッセージキューイング向き",
        "Service Busはイベントルーティング専用",
        "Event Gridはイベント駆動アーキテクチャでのイベント配信に適する",
        "Event Hubsはメール送信用"
      ],
      "answer": 2
    },
    "explanation": "Event Gridは軽量なイベントをサブスクライバーに配信するイベントルーティングサービス。Service Busはエンタープライズメッセージング、Event Hubsはビッグデータストリーミング向け。"
  },
  {
    "id": 88,
    "category": "Azureのアーキテクチャとサービス",
    "basic": {
      "question": "Azure HDInsightとは何か。",
      "choices": [
        "ストレージサービス",
        "マネージドのオープンソースビッグデータ分析サービス",
        "ID管理",
        "VPN接続"
      ],
      "answer": 1
    },
    "exam": {
      "question": "Azure上のビッグデータサービスに関する記述として正しくないものはどれか。",
      "choices": [
        "HDInsightはHadoop、Spark等をマネージドで提供する",
        "Synapse AnalyticsはDWHと分析を統合する",
        "DatabricksはApache Sparkベースの分析プラットフォーム",
        "HDInsightはメール送信サービスである"
      ],
      "answer": 3
    },
    "explanation": "HDInsightはHadoop/Spark/Hive等のオープンソース分析フレームワークをAzure上でマネージド提供する。メール送信とは無関係。"
  },
  {
    "id": 89,
    "category": "Azureのアーキテクチャとサービス",
    "basic": {
      "question": "Azure Bot Serviceの用途はどれか。",
      "choices": [
        "VM管理",
        "インテリジェントなチャットボットの構築",
        "ストレージ管理",
        "ネットワーク監視"
      ],
      "answer": 1
    },
    "exam": {
      "question": "Azure AI系サービスの組合せとして正しいものはどれか。",
      "choices": [
        "Bot Service:チャットボット、Cognitive Services:AIのAPI、Machine Learning:MLモデル構築",
        "Bot Service:データベース、Cognitive Services:ストレージ、Machine Learning:VPN",
        "Bot Service:CDN、Cognitive Services:DNS、Machine Learning:ファイル共有",
        "すべてストレージサービスである"
      ],
      "answer": 0
    },
    "explanation": "Azure AI系：Bot Serviceはチャットボット構築、Cognitive Services（AI Services）は事前構築AIのAPI提供、Machine LearningはMLモデルのトレーニング・デプロイプラットフォーム。"
  },
  {
    "id": 90,
    "category": "Azureのアーキテクチャとサービス",
    "basic": {
      "question": "Azure Cache for Redisの用途はどれか。",
      "choices": [
        "ファイル保存",
        "インメモリキャッシュによるアプリのパフォーマンス向上",
        "VM作成",
        "ID管理"
      ],
      "answer": 1
    },
    "exam": {
      "question": "キャッシュサービスに関する記述として正しいものはどれか。",
      "choices": [
        "Azure Cache for Redisはディスクベースのストレージ",
        "インメモリのため非常に高速な読み書きが可能",
        "キャッシュはパフォーマンスに影響しない",
        "永続ストレージの代替として使う"
      ],
      "answer": 1
    },
    "explanation": "Azure Cache for RedisはオープンソースRedisのマネージドサービス。インメモリデータストアのため非常に高速で、頻繁にアクセスするデータをキャッシュしバックエンドDB負荷を軽減する。"
  },
  {
    "id": 91,
    "category": "Azureの管理とガバナンス",
    "basic": {
      "question": "Azure RBACの目的はどれか。",
      "choices": [
        "ネットワーク速度の管理",
        "ユーザーに対するリソースへのアクセス制御",
        "VM作成",
        "データベース管理"
      ],
      "answer": 1
    },
    "exam": {
      "question": "Azure RBACに関する記述として、正しいものはどれか。",
      "choices": [
        "RBACはネットワーク暗号化サービスである",
        "最小権限の原則に基づきロール単位でアクセス権を付与できる",
        "すべてのユーザーに管理者権限を付与するのがベストプラクティス",
        "RBACはサブスクリプションレベルでのみ適用される"
      ],
      "answer": 1
    },
    "explanation": "Azure RBACはロール（所有者、共同作成者、閲覧者等）をユーザー/グループに割り当てリソースへのアクセスを制御する。管理グループ、サブスクリプション、リソースグループ、リソースの各レベルで適用可能。"
  },
  {
    "id": 92,
    "category": "Azureの管理とガバナンス",
    "basic": {
      "question": "Azure Cost Managementの機能はどれか。",
      "choices": [
        "VM作成",
        "コストの分析・予算設定・アラート",
        "ID管理",
        "ネットワーク監視"
      ],
      "answer": 1
    },
    "exam": {
      "question": "コスト管理に関する記述として、正しくないものはどれか。",
      "choices": [
        "コスト分析でリソース別のコストを確認できる",
        "予算を設定し超過時にアラートを受け取れる",
        "タグでコストを部門別に配分できる",
        "Azureのすべてのサービスは無料で利用できる"
      ],
      "answer": 3
    },
    "explanation": "Azure Cost Managementはコスト分析、予算設定、アラート通知、推奨事項の提供を行う。タグを活用したコスト配分も可能。Azureサービスは従量課金が基本で無料ではない。"
  },
  {
    "id": 93,
    "category": "Azureの管理とガバナンス",
    "basic": {
      "question": "Azure Policyの目的はどれか。",
      "choices": [
        "VM作成",
        "組織のルールに準拠したリソース構成を強制",
        "データベースバックアップ",
        "メール送信"
      ],
      "answer": 1
    },
    "exam": {
      "question": "Azure Policyに関する記述として、正しいものはどれか。",
      "choices": [
        "Policyはリソース作成後の監査のみ行う",
        "Policyはリソース作成時に非準拠の構成を拒否できる",
        "Policyはコスト管理ツールである",
        "Policyはネットワーク速度を制御する"
      ],
      "answer": 1
    },
    "explanation": "Azure Policyはリソースの作成時に非準拠の構成を拒否（deny）したり、既存リソースの準拠状態を監査（audit）したりできる。例：特定リージョンのみ許可、タグ必須化等。"
  },
  {
    "id": 94,
    "category": "Azureの管理とガバナンス",
    "basic": {
      "question": "Azure Portalとは何か。",
      "choices": [
        "CLI ツール",
        "Webブラウザでリソースを管理するGUI",
        "プログラミング言語",
        "物理サーバー"
      ],
      "answer": 1
    },
    "exam": {
      "question": "Azure管理ツールに関する記述として、正しいものはどれか。",
      "choices": [
        "Azure PortalでのみAzureリソースを管理できる",
        "Azure CLI、PowerShell、ARM テンプレート、REST API等でも管理可能",
        "Azure CLIはWindows専用である",
        "PowerShellはLinuxでは使えない"
      ],
      "answer": 1
    },
    "explanation": "Azureリソースの管理はPortal（GUI）以外にも、Azure CLI（クロスプラットフォーム）、PowerShell（クロスプラットフォーム）、ARMテンプレート、REST API、SDK等で可能。"
  },
  {
    "id": 95,
    "category": "Azureの管理とガバナンス",
    "basic": {
      "question": "ARMテンプレートの用途はどれか。",
      "choices": [
        "メール送信",
        "Infrastructure as Code（インフラの宣言的デプロイ）",
        "ID管理",
        "ネットワーク監視"
      ],
      "answer": 1
    },
    "exam": {
      "question": "ARMテンプレートに関する記述として、正しくないものはどれか。",
      "choices": [
        "JSON形式で記述する",
        "宣言的な構文でリソースを定義する",
        "同じテンプレートで一貫したデプロイを繰り返せる",
        "手動で毎回異なる設定を行う仕組みである"
      ],
      "answer": 3
    },
    "explanation": "ARMテンプレートはJSON形式のIaCツールで、宣言的にリソースを定義し何度でも同じ環境を再現できる。冪等性があり自動化に適する。手動設定とは対極の仕組み。"
  },
  {
    "id": 96,
    "category": "Azureの管理とガバナンス",
    "basic": {
      "question": "Azure Blueprintsの用途はどれか。",
      "choices": [
        "VM作成",
        "環境の標準構成をパッケージ化して繰り返しデプロイ",
        "ストレージ管理",
        "CDN配信"
      ],
      "answer": 1
    },
    "exam": {
      "question": "Azure Blueprintsに関する記述として、正しいものはどれか。",
      "choices": [
        "単一のリソースのみデプロイできる",
        "ポリシー、RBACロール割り当て、ARMテンプレートをパッケージ化できる",
        "ネットワーク監視ツールである",
        "Blueprintsとポリシーは同じものである"
      ],
      "answer": 1
    },
    "explanation": "Azure BlueprintsはPolicy、RBAC、ARMテンプレート、リソースグループをパッケージ化し、新環境を組織標準に沿って迅速にセットアップする。Policyの割り当て方法の一つ。"
  },
  {
    "id": 97,
    "category": "Azureの管理とガバナンス",
    "basic": {
      "question": "タグ（Tags）の用途はどれか。",
      "choices": [
        "ネットワーク暗号化",
        "リソースにメタデータを付与して整理・コスト管理",
        "VMのサイズ変更",
        "ID管理"
      ],
      "answer": 1
    },
    "exam": {
      "question": "Azureタグに関する記述として、正しくないものはどれか。",
      "choices": [
        "キーと値のペアでリソースにメタデータを付与する",
        "コスト配分やリソースの整理に活用できる",
        "タグは親リソースから子リソースに自動的に継承される",
        "ポリシーでタグの付与を強制できる"
      ],
      "answer": 2
    },
    "explanation": "Azureタグは親から子へ自動継承されない（Azure Policyで強制的に継承させることは可能）。タグはコスト配分、環境識別（dev/prod）、所有者管理等に活用する。"
  },
  {
    "id": 98,
    "category": "Azureの管理とガバナンス",
    "basic": {
      "question": "Azure Cloud Shellとは何か。",
      "choices": [
        "物理サーバー",
        "ブラウザ上で使えるCLI環境（Bash/PowerShell）",
        "ストレージサービス",
        "データベース"
      ],
      "answer": 1
    },
    "exam": {
      "question": "Azure Cloud Shellに関する記述として、正しいものはどれか。",
      "choices": [
        "ローカルにソフトウェアのインストールが必要",
        "ブラウザ上でBashまたはPowerShellが利用でき事前設定済みのツールが使える",
        "Windows OSでのみ利用可能",
        "オフラインでのみ動作する"
      ],
      "answer": 1
    },
    "explanation": "Azure Cloud ShellはAzure Portal内のブラウザベースのCLI環境。Azure CLI、PowerShell、Terraform等が事前インストールされており、ローカルへのインストール不要で即座に利用可能。"
  },
  {
    "id": 99,
    "category": "Azureの管理とガバナンス",
    "basic": {
      "question": "Azure Advisorの機能はどれか。",
      "choices": [
        "VM作成",
        "ベストプラクティスに基づく推奨事項の提供",
        "メール送信",
        "ドメイン登録"
      ],
      "answer": 1
    },
    "exam": {
      "question": "Azure Advisorが提供する推奨事項のカテゴリに含まれないものはどれか。",
      "choices": [
        "コスト",
        "セキュリティ",
        "パフォーマンス",
        "ドメイン登録"
      ],
      "answer": 3
    },
    "explanation": "Azure Advisorは信頼性、セキュリティ、パフォーマンス、コスト、オペレーショナルエクセレンスの5カテゴリでベストプラクティスに基づく推奨事項をパーソナライズして提供する。"
  },
  {
    "id": 100,
    "category": "Azureの管理とガバナンス",
    "basic": {
      "question": "Azure Service Healthの機能はどれか。",
      "choices": [
        "VM作成",
        "Azureサービスの正常性・計画メンテナンス情報の提供",
        "ストレージ管理",
        "ID管理"
      ],
      "answer": 1
    },
    "exam": {
      "question": "Azure Service Healthに関する記述として、正しくないものはどれか。",
      "choices": [
        "Azureのサービス障害情報を確認できる",
        "計画メンテナンスの事前通知を受けられる",
        "利用者のリソースに影響する問題を通知する",
        "個々のVMのCPU使用率を監視するサービスである"
      ],
      "answer": 3
    },
    "explanation": "Service HealthはAzureプラットフォームレベルの障害・メンテナンス情報を提供。個々のリソースのCPU使用率等のメトリクス監視はAzure Monitorの役割。"
  },
  {
    "id": 101,
    "category": "Azureの管理とガバナンス",
    "basic": {
      "question": "Azure Security Centerの後継サービスの名前はどれか。",
      "choices": [
        "Azure Monitor",
        "Microsoft Defender for Cloud",
        "Azure AD",
        "Azure Firewall"
      ],
      "answer": 1
    },
    "exam": {
      "question": "Microsoft Defender for Cloudに関する記述として、正しいものはどれか。",
      "choices": [
        "ストレージサービスである",
        "クラウドセキュリティポスチャー管理（CSPM）とワークロード保護を提供する",
        "ネットワーク速度を管理する",
        "VM作成専用ツールである"
      ],
      "answer": 1
    },
    "explanation": "Microsoft Defender for Cloud（旧Security Center）はCSPM（セキュリティ態勢管理）とCWP（クラウドワークロード保護）を提供。セキュリティスコア、推奨事項、脅威検出を統合。"
  },
  {
    "id": 102,
    "category": "Azureの管理とガバナンス",
    "basic": {
      "question": "多要素認証（MFA）とは何か。",
      "choices": [
        "パスワードのみで認証",
        "2つ以上の認証要素を組み合わせた認証",
        "暗号化方式",
        "ネットワーク設定"
      ],
      "answer": 1
    },
    "exam": {
      "question": "MFAの認証要素の組合せとして正しいものはどれか。",
      "choices": [
        "パスワードと別のパスワード",
        "知識（パスワード）＋所持（スマホ）＋生体（指紋）",
        "IPアドレスとMACアドレス",
        "ユーザー名を2回入力"
      ],
      "answer": 1
    },
    "explanation": "MFAは知識（パスワード等）、所持（スマートフォン、セキュリティキー等）、生体（指紋、顔認証等）のうち2つ以上を組み合わせて本人確認する。同一カテゴリの重複は不可。"
  },
  {
    "id": 103,
    "category": "Azureの管理とガバナンス",
    "basic": {
      "question": "Azure Resource Lockの用途はどれか。",
      "choices": [
        "ネットワーク暗号化",
        "リソースの誤削除・誤変更を防止",
        "VM作成",
        "メール送信"
      ],
      "answer": 1
    },
    "exam": {
      "question": "リソースロックに関する記述として、正しいものはどれか。",
      "choices": [
        "CanNotDeleteロックは変更も削除も禁止する",
        "ReadOnlyロックは読み取り専用にし変更を禁止する",
        "ロックは管理者でも解除できない",
        "ロックはリソースレベルでのみ設定可能"
      ],
      "answer": 1
    },
    "explanation": "ReadOnlyロック:読み取りのみ許可（変更・削除不可）。CanNotDeleteロック:変更は可能だが削除は不可。管理者はロックを解除できる。サブスクリプション/リソースグループ/リソースレベルで設定可能。"
  },
  {
    "id": 104,
    "category": "Azureの管理とガバナンス",
    "basic": {
      "question": "条件付きアクセスの目的はどれか。",
      "choices": [
        "ストレージ管理",
        "特定の条件（場所、デバイス等）に基づいてアクセスを制御",
        "VM作成",
        "CDN配信"
      ],
      "answer": 1
    },
    "exam": {
      "question": "条件付きアクセスに関する記述として、正しくないものはどれか。",
      "choices": [
        "ユーザーの場所に基づいてアクセスをブロックできる",
        "デバイスのコンプライアンス状態に基づいてMFAを要求できる",
        "リスクレベルに応じたアクセス制御が可能",
        "すべてのアクセスを無条件に許可する仕組みである"
      ],
      "answer": 3
    },
    "explanation": "条件付きアクセスはMicrosoft Entra IDの機能で、ユーザー/グループ、場所、デバイス状態、アプリ、リスクレベル等の条件に基づきアクセスの許可/ブロック/MFA要求を制御する。"
  },
  {
    "id": 105,
    "category": "Azureの管理とガバナンス",
    "basic": {
      "question": "Microsoft Purview（旧Azure Purview）の用途はどれか。",
      "choices": [
        "VM管理",
        "データガバナンスとコンプライアンス管理",
        "ネットワーク監視",
        "CDN"
      ],
      "answer": 1
    },
    "exam": {
      "question": "Microsoft Purviewに関する記述として、正しいものはどれか。",
      "choices": [
        "仮想マシン管理サービスである",
        "データの分類、ラベル付け、ガバナンスを統合的に管理するサービスである",
        "ネットワークファイアウォールである",
        "ストレージの暗号化専用ツールである"
      ],
      "answer": 1
    },
    "explanation": "Microsoft Purviewはデータガバナンスプラットフォームで、組織全体のデータの検出・分類・ラベル付け・アクセス管理を統合管理。コンプライアンスとデータ主権の確保に活用する。"
  },
  {
    "id": 106,
    "category": "Azureの管理とガバナンス",
    "basic": {
      "question": "Azure Pricing Calculatorの用途はどれか。",
      "choices": [
        "リソースの作成",
        "Azureサービスの料金見積もり",
        "ID管理",
        "ネットワーク監視"
      ],
      "answer": 1
    },
    "exam": {
      "question": "料金見積もりツールに関する記述として、正しいものはどれか。",
      "choices": [
        "Pricing Calculatorは事前にサービスの月額コストを見積もれる",
        "TCO Calculatorはリソースのデプロイに使う",
        "Pricing Calculatorは実際の請求書と同じ",
        "TCO CalculatorはAzure内のコスト分析ツールである"
      ],
      "answer": 0
    },
    "explanation": "Pricing CalculatorはAzureサービスの構成を選択して月額コストを事前見積もりするツール。TCO Calculatorはオンプレミスとクラウドの総所有コスト比較用。いずれもリソースデプロイ機能はない。"
  },
  {
    "id": 107,
    "category": "Azureの管理とガバナンス",
    "basic": {
      "question": "予約インスタンス（Reserved Instances）の利点はどれか。",
      "choices": [
        "従量課金より高い",
        "1年または3年の予約で大幅な割引を受けられる",
        "柔軟性が高い",
        "無料で利用できる"
      ],
      "answer": 1
    },
    "exam": {
      "question": "コスト削減策に関する記述として、正しくないものはどれか。",
      "choices": [
        "予約インスタンスで最大72%の割引が得られる",
        "Azure Hybrid Benefitで既存ライセンスを活用できる",
        "スポットVMは余剰容量を割引価格で利用できる",
        "すべてのリソースは予約インスタンスが最適である"
      ],
      "answer": 3
    },
    "explanation": "予約は長期利用が確実な場合に有効だが、需要が変動するワークロードには従量課金やスポットVMの方が適切。用途に応じた使い分けが重要。"
  },
  {
    "id": 108,
    "category": "Azureの管理とガバナンス",
    "basic": {
      "question": "Azure Monitorのアラート機能の目的はどれか。",
      "choices": [
        "VM作成",
        "異常を検知して通知する",
        "ドメイン購入",
        "ストレージ管理"
      ],
      "answer": 1
    },
    "exam": {
      "question": "Azure Monitorのアラートに関する記述として、正しいものはどれか。",
      "choices": [
        "アラートは手動確認でのみ検知する",
        "メトリクスやログの条件に基づいて自動的にアラートを発報できる",
        "アラートはメール通知のみ対応",
        "アラートはコスト管理機能である"
      ],
      "answer": 1
    },
    "explanation": "Azure Monitorのアラートはメトリクスやログクエリの条件に基づき自動発報。通知方法はメール、SMS、Webhook、Logic Apps、Azure Functions等を選択可能。"
  },
  {
    "id": 109,
    "category": "Azureの管理とガバナンス",
    "basic": {
      "question": "Azure Log Analytics（ログ分析）の用途はどれか。",
      "choices": [
        "VM作成",
        "ログデータのクエリと分析",
        "メール送信",
        "ドメイン登録"
      ],
      "answer": 1
    },
    "exam": {
      "question": "Log Analyticsに関する記述として、正しくないものはどれか。",
      "choices": [
        "KQLを使ってログを照会できる",
        "Azure Monitorの一部として機能する",
        "複数のソースからログを収集できる",
        "リアルタイムでVMを作成するサービスである"
      ],
      "answer": 3
    },
    "explanation": "Log Analyticsワークスペースはログデータを収集し、KQL（Kusto Query Language）で照会・分析する。Azure Monitorの中核コンポーネントで、VM/アプリ/ネットワーク等のログを統合分析。"
  },
  {
    "id": 110,
    "category": "Azureの管理とガバナンス",
    "basic": {
      "question": "ゼロトラストセキュリティモデルの原則はどれか。",
      "choices": [
        "社内ネットワークは常に信頼する",
        "何も信頼せず常に検証する",
        "パスワードのみで認証",
        "ファイアウォールだけで防御"
      ],
      "answer": 1
    },
    "exam": {
      "question": "ゼロトラストに関する記述として、正しいものはどれか。",
      "choices": [
        "社内ネットワーク内であれば検証不要",
        "明示的に検証し、最小権限を付与し、侵害を想定する",
        "境界防御のみで十分",
        "ゼロトラストはクラウドには適用されない"
      ],
      "answer": 1
    },
    "explanation": "ゼロトラストの3原則：明示的に検証する、最小権限アクセスを使用する、侵害を想定する。ネットワークの内外を問わずすべてのアクセスを検証する考え方。"
  },
  {
    "id": 111,
    "category": "Azureの管理とガバナンス",
    "basic": {
      "question": "多層防御（Defense in Depth）とは何か。",
      "choices": [
        "1つの防御層のみ",
        "複数のセキュリティ層を重ねて保護する考え方",
        "防御なし",
        "物理セキュリティのみ"
      ],
      "answer": 1
    },
    "exam": {
      "question": "多層防御の層に含まれないものはどれか。",
      "choices": [
        "物理セキュリティ",
        "ID とアクセス",
        "ネットワーク",
        "マーケティング"
      ],
      "answer": 3
    },
    "explanation": "多層防御の層：物理→ID/アクセス→境界→ネットワーク→コンピューティング→アプリケーション→データ。各層で異なるセキュリティ対策を重ね、1層突破されても他層で防御する。"
  },
  {
    "id": 112,
    "category": "Azureの管理とガバナンス",
    "basic": {
      "question": "Azure Sentinelの用途はどれか。",
      "choices": [
        "VM作成",
        "SIEM（セキュリティ情報イベント管理）とSOAR",
        "ストレージ",
        "CDN"
      ],
      "answer": 1
    },
    "exam": {
      "question": "Microsoft Sentinelに関する記述として、正しいものはどれか。",
      "choices": [
        "ストレージサービスである",
        "クラウドネイティブのSIEMで脅威検出・調査・対応を自動化する",
        "ネットワーク速度を管理する",
        "VM作成ツールである"
      ],
      "answer": 1
    },
    "explanation": "Microsoft Sentinel（旧Azure Sentinel）はクラウドネイティブのSIEM/SOARサービス。AIによる脅威検出、インシデント調査、自動応答（プレイブック）を提供する。"
  },
  {
    "id": 113,
    "category": "Azureの管理とガバナンス",
    "basic": {
      "question": "コンプライアンスマネージャーの役割はどれか。",
      "choices": [
        "VM管理",
        "規制要件への準拠状況の評価・管理",
        "ネットワーク監視",
        "CDN"
      ],
      "answer": 1
    },
    "exam": {
      "question": "Azureのコンプライアンスに関する記述として、正しくないものはどれか。",
      "choices": [
        "Azure は多数の業界標準・規制に準拠している（ISO、SOC、GDPR等）",
        "コンプライアンスマネージャーで準拠状況を評価できる",
        "Trust Centerで Azureのコンプライアンス情報を確認できる",
        "Azureを使えば利用者のコンプライアンス責任はすべて免除される"
      ],
      "answer": 3
    },
    "explanation": "Azureはプラットフォームとして多数の認証を取得しているが、利用者のデータ管理やアプリケーション構成に関するコンプライアンス責任は共有責任モデルに基づき利用者にも残る。"
  },
  {
    "id": 114,
    "category": "Azureの管理とガバナンス",
    "basic": {
      "question": "Azure Activity Log（アクティビティログ）で確認できるものはどれか。",
      "choices": [
        "リソースのCPU使用率",
        "誰がいつどのリソースを操作したか",
        "ストレージの空き容量",
        "ネットワーク帯域"
      ],
      "answer": 1
    },
    "exam": {
      "question": "Activity Logに関する記述として、正しいものはどれか。",
      "choices": [
        "リソースレベルのパフォーマンスメトリクスを記録する",
        "サブスクリプションレベルのイベント（作成、更新、削除等）を記録する",
        "ログの保持は無期限で削除できない",
        "アプリケーション内部のエラーログを記録する"
      ],
      "answer": 1
    },
    "explanation": "Activity Logはサブスクリプションレベルの管理操作（誰が、いつ、何を作成/変更/削除したか）を記録。デフォルト90日保持。リソースのメトリクスはAzure Monitor、アプリログはApplication Insights。"
  },
  {
    "id": 115,
    "category": "Azureの管理とガバナンス",
    "basic": {
      "question": "Azure Trust Centerの目的はどれか。",
      "choices": [
        "VM作成",
        "Azureのセキュリティ・プライバシー・コンプライアンス情報の提供",
        "ストレージ管理",
        "CDN"
      ],
      "answer": 1
    },
    "exam": {
      "question": "Trust Centerに関する記述として、正しくないものはどれか。",
      "choices": [
        "Azureのセキュリティ慣行に関する情報を提供する",
        "監査レポートやコンプライアンス認証の情報がある",
        "プライバシーに関するMicrosoftのポリシーが記載されている",
        "Azureリソースの作成と管理を行う管理ポータルである"
      ],
      "answer": 3
    },
    "explanation": "Trust CenterはMicrosoftのセキュリティ・プライバシー・コンプライアンスに関する情報を提供するWebサイト。リソースの管理ポータルはAzure Portal。"
  },
  {
    "id": 116,
    "category": "Azureの管理とガバナンス",
    "basic": {
      "question": "Azure Monitorでメトリクスとは何を指すか。",
      "choices": [
        "テキストログ",
        "数値で表されるパフォーマンスデータ（CPU使用率等）",
        "ユーザーID",
        "ネットワークアドレス"
      ],
      "answer": 1
    },
    "exam": {
      "question": "メトリクスとログの違いに関する記述として、正しいものはどれか。",
      "choices": [
        "メトリクスは数値の時系列データでリアルタイム性が高い",
        "ログは数値データのみ含む",
        "メトリクスはテキストデータのみ含む",
        "両者に違いはない"
      ],
      "answer": 0
    },
    "explanation": "メトリクスは一定間隔で収集される数値の時系列データ（CPU%、メモリ使用量等）でリアルタイム性が高い。ログはイベントやテキスト情報を含む構造化/非構造化データで詳細分析向け。"
  },
  {
    "id": 117,
    "category": "Azureの管理とガバナンス",
    "basic": {
      "question": "Azure上で保存データの暗号化に使われるのはどれか。",
      "choices": [
        "Azure Storage Service Encryption（SSE）",
        "Azure CDN",
        "Azure DNS",
        "Azure DevOps"
      ],
      "answer": 0
    },
    "exam": {
      "question": "Azureの暗号化に関する記述として、正しいものはどれか。",
      "choices": [
        "保存データ（at rest）はデフォルトで暗号化されない",
        "Azure Storageはデフォルトで256ビットAES暗号化が適用される",
        "転送中データ（in transit）は暗号化できない",
        "暗号化キーの管理はMicrosoftのみが行える"
      ],
      "answer": 1
    },
    "explanation": "Azure Storageはデフォルトで保存データを256ビットAESで暗号化（SSE）。転送中はTLS/SSL。暗号化キーはMicrosoft管理キーまたは利用者のKey Vault管理キーを選択可能。"
  },
  {
    "id": 118,
    "category": "Azureの管理とガバナンス",
    "basic": {
      "question": "サービスプリンシパルとは何か。",
      "choices": [
        "人間のユーザーアカウント",
        "アプリケーションやサービスが使用するID",
        "物理サーバー",
        "ネットワーク機器"
      ],
      "answer": 1
    },
    "exam": {
      "question": "IDの種類に関する記述として、正しいものはどれか。",
      "choices": [
        "サービスプリンシパルは人間のログインにのみ使用する",
        "マネージドIDはAzureが自動的に管理するサービス用ID",
        "すべてのIDは手動でパスワード管理が必要",
        "ゲストユーザーはリソースにアクセスできない"
      ],
      "answer": 1
    },
    "explanation": "マネージドIDはAzureが自動的に作成・管理するサービス用ID。資格情報の手動管理が不要で安全。サービスプリンシパルはアプリ用ID、ゲストユーザーは外部組織からの招待ユーザー。"
  },
  {
    "id": 119,
    "category": "Azureの管理とガバナンス",
    "basic": {
      "question": "Microsoft Defender for Cloudのセキュリティスコアとは何か。",
      "choices": [
        "課金額",
        "セキュリティ態勢の数値評価（高いほど良い）",
        "ネットワーク速度",
        "ストレージ容量"
      ],
      "answer": 1
    },
    "exam": {
      "question": "セキュリティスコアに関する記述として、正しくないものはどれか。",
      "choices": [
        "推奨事項を実装するとスコアが向上する",
        "スコアが高いほどセキュリティリスクが低い",
        "すべてのリソースのセキュリティ態勢を評価する",
        "スコアが100%であればあらゆる攻撃を完全に防げる"
      ],
      "answer": 3
    },
    "explanation": "セキュリティスコアはセキュリティ態勢の相対評価であり、100%でも完全な防御を保証するものではない。推奨事項の実装でスコアが向上し、リスク軽減に寄与する。"
  },
  {
    "id": 120,
    "category": "Azureの管理とガバナンス",
    "basic": {
      "question": "Azure Information Protection（AIP）の目的はどれか。",
      "choices": [
        "VM管理",
        "ドキュメントやメールの分類・ラベル付け・保護",
        "ネットワーク監視",
        "CDN"
      ],
      "answer": 1
    },
    "exam": {
      "question": "データ保護に関する記述として、正しいものはどれか。",
      "choices": [
        "Azure Information Protectionはドキュメントに機密度ラベルを付与し暗号化・アクセス制限ができる",
        "データ保護はネットワークレベルのみで行う",
        "暗号化されたデータは誰でもアクセスできる",
        "ラベル付けは手動のみ可能で自動化できない"
      ],
      "answer": 0
    },
    "explanation": "Azure Information Protection（現Microsoft Purview Information Protection）は機密度ラベルでドキュメントを自動/手動分類し、暗号化やアクセス制限で保護する。"
  },
  {
    "id": 121,
    "category": "Azureの管理とガバナンス",
    "basic": {
      "question": "Azure Automationの用途はどれか。",
      "choices": [
        "メール送信",
        "クラウドリソースの自動運用管理（Runbook等）",
        "ドメイン購入",
        "CDN配信"
      ],
      "answer": 1
    },
    "exam": {
      "question": "Azure Automationに関する記述として、正しいものはどれか。",
      "choices": [
        "手動操作のみをサポートする",
        "Runbookでプロセスを自動化し、更新管理やスケジュール実行が可能",
        "ストレージサービスである",
        "ID管理専用ツールである"
      ],
      "answer": 1
    },
    "explanation": "Azure AutomationはRunbook（PowerShell/Python）でプロセスを自動化。VM起動/停止スケジュール、更新管理、構成管理等の定型運用タスクを自動化する。"
  },
  {
    "id": 122,
    "category": "Azureの管理とガバナンス",
    "basic": {
      "question": "Azure のサポートプランで最も応答時間が短いのはどれか。",
      "choices": [
        "Basic",
        "Developer",
        "Standard",
        "Premier/Unified"
      ],
      "answer": 3
    },
    "exam": {
      "question": "Azureサポートプランに関する記述として、正しくないものはどれか。",
      "choices": [
        "Basicプランは全Azureユーザーに無料提供",
        "Developerプランは非本番環境向け",
        "Premierプランは重大な影響の場合15分以内の応答",
        "すべてのプランで24/7のテクニカルサポートが含まれる"
      ],
      "answer": 3
    },
    "explanation": "24/7テクニカルサポートはStandard以上。Basicは無料だがテクニカルサポートなし。DeveloperはBusiness hours内のメールサポート。Premier/Unifiedは最短15分応答。"
  },
  {
    "id": 123,
    "category": "Azureの管理とガバナンス",
    "basic": {
      "question": "Azure でリソースに影響を与えるコスト要因はどれか。",
      "choices": [
        "ユーザーの名前",
        "リージョン、リソースタイプ、使用量",
        "メールアドレス",
        "パスワードの長さ"
      ],
      "answer": 1
    },
    "exam": {
      "question": "Azureのコストに影響する要因として、正しいものの組合せはどれか。\n\nA. リージョンの選択\nB. リソースタイプとサイズ\nC. 送信データ転送量\nD. ユーザーのメールアドレス",
      "choices": [
        "AとBとC",
        "AとD",
        "BとD",
        "CとD"
      ],
      "answer": 0
    },
    "explanation": "Azureのコストはリージョン（地域による価格差）、リソースタイプ/サイズ、使用量、送信データ転送量等で決まる。受信データは通常無料、送信データに課金される。"
  },
  {
    "id": 124,
    "category": "Azureの管理とガバナンス",
    "basic": {
      "question": "Azure の無料アカウントに含まれるものはどれか。",
      "choices": [
        "無制限のVM",
        "12ヶ月間の一部サービス無料枠とクレジット",
        "永久無料の全サービス",
        "物理サーバー"
      ],
      "answer": 1
    },
    "exam": {
      "question": "Azure無料アカウントに関する記述として、正しくないものはどれか。",
      "choices": [
        "30日間使える200ドルのクレジットが付与される",
        "12ヶ月間の人気サービスの無料枠がある",
        "一部のサービスは永続的に無料（Always Free）",
        "すべてのサービスが無制限に無料で利用できる"
      ],
      "answer": 3
    },
    "explanation": "Azure無料アカウントは200ドル/30日のクレジット、12ヶ月無料の人気サービス（VM、ストレージ等の限定枠）、Always Freeサービス（一部）を提供。無制限無料ではない。"
  },
  {
    "id": 125,
    "category": "Azureの管理とガバナンス",
    "basic": {
      "question": "パスワードレス認証の例はどれか。",
      "choices": [
        "パスワードのみ",
        "Windows Hello、FIDOキー、Microsoft Authenticator",
        "セキュリティの質問",
        "秘密の答え"
      ],
      "answer": 1
    },
    "exam": {
      "question": "パスワードレス認証に関する記述として、正しいものはどれか。",
      "choices": [
        "パスワードより安全性が低い",
        "生体認証や物理キーを使いパスワードなしで安全に認証する",
        "すべてのシステムで利用可能",
        "Microsoft Entra IDではサポートされていない"
      ],
      "answer": 1
    },
    "explanation": "パスワードレス認証はWindows Hello（生体認証）、FIDOセキュリティキー、Microsoft Authenticatorアプリ等を使用。パスワード漏洩リスクを排除し安全性を向上させる。"
  },
  {
    "id": 126,
    "category": "Azureの管理とガバナンス",
    "basic": {
      "question": "Azure Policy イニシアティブとは何か。",
      "choices": [
        "単一のポリシー",
        "複数のポリシーをグループ化したもの",
        "VMの種類",
        "ストレージタイプ"
      ],
      "answer": 1
    },
    "exam": {
      "question": "Policy イニシアティブに関する記述として、正しいものはどれか。",
      "choices": [
        "イニシアティブは1つのポリシーしか含められない",
        "関連する複数のポリシーをまとめて管理・割り当てできる",
        "イニシアティブはネットワーク設定ツールである",
        "イニシアティブとポリシーに違いはない"
      ],
      "answer": 1
    },
    "explanation": "Policy イニシアティブ（ポリシーセット）は関連する複数のポリシー定義をグループ化し、一括で割り当て・管理できる。例：CIS ベンチマークのポリシー群を1つのイニシアティブに。"
  },
  {
    "id": 127,
    "category": "Azureの管理とガバナンス",
    "basic": {
      "question": "GDPR とは何か。",
      "choices": [
        "Azureのサービス名",
        "EUの一般データ保護規則",
        "プログラミング言語",
        "ネットワーク機器"
      ],
      "answer": 1
    },
    "exam": {
      "question": "コンプライアンス規制に関する記述として、正しくないものはどれか。",
      "choices": [
        "GDPRはEU市民の個人データ保護を規定する",
        "AzureはGDPRに対応したサービスを提供している",
        "コンプライアンスの責任は共有責任モデルに基づく",
        "Azureを使えば利用者は自動的にすべての規制に準拠する"
      ],
      "answer": 3
    },
    "explanation": "Azureはプラットフォームとして各種規制に対応するが、利用者が構築するアプリやデータの管理に関する準拠責任は利用者にもある（共有責任モデル）。"
  },
  {
    "id": 128,
    "category": "Azureの管理とガバナンス",
    "basic": {
      "question": "シングルサインオン（SSO）の利点はどれか。",
      "choices": [
        "アプリごとに別々のパスワードが必要",
        "1回の認証で複数のアプリにアクセスできる",
        "セキュリティが下がる",
        "認証が不要になる"
      ],
      "answer": 1
    },
    "exam": {
      "question": "SSOに関する記述として、正しくないものはどれか。",
      "choices": [
        "ユーザーの利便性が向上する",
        "パスワード管理の負担が軽減される",
        "Microsoft Entra IDでSSOを実現できる",
        "SSOを導入するとセキュリティは必ず低下する"
      ],
      "answer": 3
    },
    "explanation": "SSOは利便性向上とパスワード管理負担軽減に加え、一元的なアクセス管理やMFAとの組み合わせでセキュリティを向上させることもできる。適切に実装すれば安全性は向上する。"
  },
  {
    "id": 129,
    "category": "Azureの管理とガバナンス",
    "basic": {
      "question": "Azure Bicepとは何か。",
      "choices": [
        "プログラミング言語",
        "ARMテンプレートを簡潔に記述するためのDSL",
        "ストレージサービス",
        "ID管理"
      ],
      "answer": 1
    },
    "exam": {
      "question": "Infrastructure as Code（IaC）に関する記述として、正しいものはどれか。",
      "choices": [
        "IaCは手動でリソースを作成する方法",
        "BicepはARMテンプレートのJSON記述を簡潔にしたドメイン固有言語",
        "TerraformはAzure専用ツール",
        "IaCでは再現性のあるデプロイは実現できない"
      ],
      "answer": 1
    },
    "explanation": "BicepはARMテンプレート（JSON）を簡潔に記述できるDSL。TerraformはマルチクラウドIaCツール。IaCはインフラを宣言的コードで定義し再現性・自動化を実現する。"
  },
  {
    "id": 130,
    "category": "Azureの管理とガバナンス",
    "basic": {
      "question": "Azure DevTest Labsの用途はどれか。",
      "choices": [
        "本番環境の運用",
        "開発・テスト環境の迅速な構築とコスト管理",
        "メール送信",
        "CDN"
      ],
      "answer": 1
    },
    "exam": {
      "question": "DevTest Labsに関する記述として、正しいものはどれか。",
      "choices": [
        "本番ワークロード専用サービスである",
        "自動シャットダウンやクォータ設定でテスト環境のコストを管理できる",
        "ストレージサービスである",
        "ネットワーク監視ツールである"
      ],
      "answer": 1
    },
    "explanation": "Azure DevTest Labsは開発・テスト環境を迅速に構築し、自動シャットダウン、VM数制限（クォータ）、再利用可能な テンプレート等でコストと管理を最適化するサービス。"
  },
  {
    "id": 131,
    "category": "Azureの管理とガバナンス",
    "basic": {
      "question": "データ主権（Data Sovereignty）とは何か。",
      "choices": [
        "データの暗号化方式",
        "データが保存される国の法律にデータが従うこと",
        "ネットワーク速度",
        "プログラミング手法"
      ],
      "answer": 1
    },
    "exam": {
      "question": "データ主権に関する記述として、正しいものはどれか。",
      "choices": [
        "データはどのリージョンに保存しても法律は同じ",
        "リージョンの選択によりデータが保存される国の法律が適用される",
        "Azureではデータの保存場所を選択できない",
        "データ主権は企業に影響しない"
      ],
      "answer": 1
    },
    "explanation": "データ主権はデータが物理的に保存される国の法律が適用される概念。Azureのリージョン選択でデータの保存場所を制御し、GDPRや各国規制に対応する。"
  },
  {
    "id": 132,
    "category": "Azureの管理とガバナンス",
    "basic": {
      "question": "Azure Application Insightsの用途はどれか。",
      "choices": [
        "VM管理",
        "アプリケーションのパフォーマンス監視（APM）",
        "ドメイン購入",
        "ストレージ管理"
      ],
      "answer": 1
    },
    "exam": {
      "question": "Application Insightsに関する記述として、正しくないものはどれか。",
      "choices": [
        "Webアプリのパフォーマンスと例外を監視する",
        "ユーザーの行動分析ができる",
        "Azure Monitorの一部として機能する",
        "物理サーバーのハードウェア障害を検出するサービスである"
      ],
      "answer": 3
    },
    "explanation": "Application InsightsはAPM（アプリケーションパフォーマンス管理）サービスでWebアプリのレスポンス時間、エラー率、依存関係、ユーザー行動を監視。Azure Monitorの一部。"
  },
  {
    "id": 133,
    "category": "Azureの管理とガバナンス",
    "basic": {
      "question": "外部IDとの連携に使用するMicrosoft Entra IDの機能はどれか。",
      "choices": [
        "Blob Storage",
        "B2B/B2Cコラボレーション",
        "VPN Gateway",
        "CDN"
      ],
      "answer": 1
    },
    "exam": {
      "question": "Microsoft Entra External IDに関する記述として、正しいものはどれか。",
      "choices": [
        "社内ユーザーの管理のみを行う",
        "B2Bで外部パートナーを招待し、B2Cで顧客向けIDを管理できる",
        "ストレージサービスである",
        "ネットワーク接続サービスである"
      ],
      "answer": 1
    },
    "explanation": "Microsoft Entra External ID（旧Azure AD B2B/B2C）はB2Bで外部パートナーにリソースアクセスを許可し、B2Cで消費者向けアプリの認証（ソーシャルログイン等）を提供する。"
  },
  {
    "id": 134,
    "category": "Azureの管理とガバナンス",
    "basic": {
      "question": "Azureの課金に影響しないものはどれか。",
      "choices": [
        "リソースの使用量",
        "リージョン",
        "受信データ転送",
        "送信データ転送"
      ],
      "answer": 2
    },
    "exam": {
      "question": "Azureのデータ転送コストに関する記述として、正しいものはどれか。",
      "choices": [
        "受信（イングレス）も送信（エグレス）も同額で課金される",
        "受信データは通常無料だが送信データは課金される",
        "送信データは常に無料である",
        "データ転送量はコストに影響しない"
      ],
      "answer": 1
    },
    "explanation": "Azureでは受信データ（インバウンド/イングレス）は通常無料。送信データ（アウトバウンド/エグレス）はリージョン外への転送量に応じて課金される。"
  },
  {
    "id": 135,
    "category": "Azureの管理とガバナンス",
    "basic": {
      "question": "Azure 管理グループのルート管理グループとは何か。",
      "choices": [
        "最下位の管理単位",
        "すべての管理グループとサブスクリプションの最上位親",
        "リソースグループ",
        "ストレージアカウント"
      ],
      "answer": 1
    },
    "exam": {
      "question": "管理グループに関する記述として、正しくないものはどれか。",
      "choices": [
        "管理グループは最大6レベルまでネストできる",
        "ルート管理グループは自動的に存在する",
        "管理グループのポリシーは配下のサブスクリプションに継承される",
        "管理グループは1つしか作成できない"
      ],
      "answer": 3
    },
    "explanation": "管理グループは複数作成可能で最大6レベル（ルート含む）までネスト可能。ルート管理グループは自動存在し、そこに設定したポリシー/RBACは配下の全サブスクリプションに継承される。"
  }
]